6111work/PSets/finale/fec.v
module fec 	(
				data_in,
				fec_out
			);
	// calculate the fec combinationally
	localparam DATA_WIDTH = 48;

	input	   [DATA_WIDTH - 1:0]   data_in;
	output     [(2*DATA_WIDTH-1):0] fec_out;

	wire	   [DATA_WIDTH - 1:0]   data_in_rev;
	wire       [(2*DATA_WIDTH-1):0] fec_out_rev;

	// assign the first 6 values of the fec because x[n-3] is not defined
	// do it so p[1] and p[0] are reversed as we will reverse later on
	assign fec_out_rev[1] = data_in_rev[0];
	assign fec_out_rev[0] = data_in_rev[0];

	assign fec_out_rev[3] = data_in_rev[1] ^ data_in_rev[0];
	assign fec_out_rev[2] = data_in_rev[1];

	assign fec_out_rev[5] = data_in_rev[2] ^ data_in_rev[1] ^ data_in_rev[0];
	assign fec_out_rev[4] = data_in_rev[2] ^ data_in_rev[0];

	// generate the rest of the fec
	generate
		genvar i;
		for (i = 3; i < DATA_WIDTH; i = i + 1)
		begin:fec_rev_gen
			assign fec_out_rev[2*i + 1]     = data_in_rev[i] ^ data_in_rev[i-1] ^ data_in_rev[i-2] ^ data_in_rev[i-3];
			assign fec_out_rev[2*i]         = data_in_rev[i] ^ data_in_rev[i-2] ^ data_in_rev[i-3];
		end
	endgenerate

	// reverse the fec so it is the correct endianness
	generate
		genvar j;
		for (j = 0; j < 2*DATA_WIDTH; j = j + 1)
		begin:fec_gen
			assign fec_out[j] = fec_out_rev[(2*DATA_WIDTH-1)-j];
		end
	endgenerate

	// revese the data input endianness
	generate
		genvar k;
		for (k = 0; k < DATA_WIDTH; k = k + 1)
		begin:input_rev
			assign data_in_rev[k] = data_in[(DATA_WIDTH-1)-k];		
		end
	endgenerate

endmodule

6111work/PSets/finale/crc.v
module crc(clk_in, start_in, data_in, done_out, r_out);
    input clk_in, start_in, data_in;
    output done_out;
    output [15:0] r_out;

    reg start_latch          = 1'b0;

    reg  [15:0] r_out        = 16'hFFFF;
    // determines number of clock cycles before done signal is asserted
    reg  [6:0] counter       = 7'd31;
    // the next value of the counter
    wire [6:0] counter_next;
    // done signal is asserted when we get to 64
    // this prevents any potential glitches 
    assign done_out = counter_next[6];
    // increment the counter
    assign counter_next = counter + 1;
    always @ (posedge clk_in)
    begin        
    if (start_in)
        begin
            // reset the vals
            start_latch  <= 1'b1;
            r_out        <= 16'hFFFF;
            counter      <= 7'd31;
        end
        else 
        begin
            if (start_latch & ~(counter_next[6]))
            begin
                // create the gen polynomial
                r_out <= { r_out[15] ^ r_out[14] ^ data_in, 
                            r_out[13:2], 
                            r_out[15] ^ data_in ^ r_out[1], 
                            r_out[0], 
                            r_out[15] ^ data_in
                      };
                counter <= counter_next;
            end
            else 
            begin
                start_latch <= 1'b0;
                // If you don't want done_out to stay high, uncomment below
                // counter <= 7'd32;
            end
        end
    end

endmodule

6111work/PSets/finale/fec_pipelined.v
module fec_pipelined(clk_in, start_in, data_in, done_out, fec_out, fsm_state_out, cycle_count_out);
	input 			clk_in;
	input  			start_in;
	input  			data_in;
	output 			done_out;
	output   [95:0] fec_out;
	output 	[179:0] fsm_state_out;
	output 	  [5:0] cycle_count_out;

	localparam CRC_WIDTH = 16;

	wire     [CRC_WIDTH-1:0] crc;

	// output of the crc combined with data which will go to fec
	wire     [47:0] fec_input_intermediate;
	// shift register for data
	reg      [31:0] data_shift_reg = 32'b0;
	// counter which detemines no of clock cycles
	reg       [5:0] cycle_count_out = 0;
	// fun little easter egg
	wire    [179:0] msg_for_the_ta;

	assign msg_for_the_ta = 180'h073032108111118101032121111117032071105109046;
	// as I'm doing the fec encoding in one clock cycle, is there a state?
	assign fsm_state_out  = msg_for_the_ta;

	crc crc1(
				.clk_in(clk_in),
				.start_in(start_in),
				.data_in(data_in),
				.done_out(done_out),
				.r_out(crc)
			);

	// concatenate the bits
	assign fec_input_intermediate = {data_shift_reg, crc};

	fec f1  (
				.data_in(fec_input_intermediate),
				.fec_out(fec_out)
			);

	always @(posedge clk_in or posedge start_in) 
	begin
		if (start_in) 
		begin
			cycle_count_out <= 6'b0;
			data_shift_reg  <= 32'b0;	
		end
		else if (~done_out)
		begin
			cycle_count_out <= cycle_count_out + 1;
			data_shift_reg  <= {data_shift_reg[30:0], data_in};			
		end
	end

endmodule

`include "crc.v"
`include "fec.v"

6111work/PSets/finale/fec_pipelined_tb.v
module fec_pipelined_tb;
	reg clk = 1'b0;
	reg  [31:0] data = 32'h03010203;
	wire [95:0] correct_fec = 96'h000E8C037C0DF00E828C0E5E;
	wire correct;

	assign correct = (correct_fec == fec);
	
	reg   start;
	reg   serial;
	wire  done;
	wire  [95:0] fec;
	wire  [179:0] fsm_state;
	wire  [5:0] cycle_count;
    reg         data_clk;

	fec_pipelined fp1(
						.clk_in(clk),
						.start_in(start),
						.data_in(serial),
						.done_out(done),
						.fec_out(fec),
						.fsm_state_out(fsm_state),
						.cycle_count_out(cycle_count)
					);

   initial 
   begin   // system clock
      forever #5 clk = !clk;
   end
      
   initial 
   begin   // data_clk, ensures setup time met               
      #2
      forever #5 data_clk = !data_clk;
   end
	
	integer i;

	initial
	begin		
		$dumpfile("fec_test.vcd");
		$dumpvars(0, fec_pipelined_tb);
		clk = 0;
		data_clk = 0;
		start = 0;
		serial = 0;
		// Wait 100 ns for global reset to finish
		#100;

		// start
		start=1;
		#10 start = 0;
		start=1;
      	#10 
      	start = 0;
		#5;

		for (i=0; i<32; i=i+1)
		begin
			serial = data[31];
			@(posedge data_clk) data = {data[30:0],1'b0};     
		end

		#100;
		$finish;
	end

endmodule

6111work/PSets/finale/fec_test.vcd
$date
	Sun Oct 14 21:50:58 2018
$end
$version
	Icarus Verilog
$end
$timescale
	1s
$end
$scope module fec_pipelined_tb $end
$var wire 96 ! correct_fec [95:0] $end
$var wire 180 " fsm_state [179:0] $end
$var wire 96 # fec [95:0] $end
$var wire 1 $ done $end
$var wire 6 % cycle_count [5:0] $end
$var wire 1 & correct $end
$var reg 1 ' clk $end
$var reg 32 ( data [31:0] $end
$var reg 1 ) data_clk $end
$var reg 1 * serial $end
$var reg 1 + start $end
$var integer 32 , i [31:0] $end
$scope module fp1 $end
$var wire 1 ' clk_in $end
$var wire 1 * data_in $end
$var wire 180 - fsm_state_out [179:0] $end
$var wire 180 . msg_for_the_ta [179:0] $end
$var wire 1 + start_in $end
$var wire 96 / fec_out [95:0] $end
$var wire 48 0 fec_input_intermediate [47:0] $end
$var wire 1 $ done_out $end
$var wire 16 1 crc [15:0] $end
$var reg 6 2 cycle_count_out [5:0] $end
$var reg 32 3 data_shift_reg [31:0] $end
$scope module crc1 $end
$var wire 1 ' clk_in $end
$var wire 1 * data_in $end
$var wire 1 + start_in $end
$var wire 1 $ done_out $end
$var wire 7 4 counter_next [6:0] $end
$var reg 7 5 counter [6:0] $end
$var reg 16 6 r_out [15:0] $end
$var reg 1 7 start_latch $end
$upscope $end
$scope module f1 $end
$var wire 48 8 data_in [47:0] $end
$var wire 96 9 fec_out_rev [95:0] $end
$var wire 96 : fec_out [95:0] $end
$var wire 48 ; data_in_rev [47:0] $end
$scope begin fec_gen[0] $end
$upscope $end
$scope begin fec_gen[1] $end
$upscope $end
$scope begin fec_gen[2] $end
$upscope $end
$scope begin fec_gen[3] $end
$upscope $end
$scope begin fec_gen[4] $end
$upscope $end
$scope begin fec_gen[5] $end
$upscope $end
$scope begin fec_gen[6] $end
$upscope $end
$scope begin fec_gen[7] $end
$upscope $end
$scope begin fec_gen[8] $end
$upscope $end
$scope begin fec_gen[9] $end
$upscope $end
$scope begin fec_gen[10] $end
$upscope $end
$scope begin fec_gen[11] $end
$upscope $end
$scope begin fec_gen[12] $end
$upscope $end
$scope begin fec_gen[13] $end
$upscope $end
$scope begin fec_gen[14] $end
$upscope $end
$scope begin fec_gen[15] $end
$upscope $end
$scope begin fec_gen[16] $end
$upscope $end
$scope begin fec_gen[17] $end
$upscope $end
$scope begin fec_gen[18] $end
$upscope $end
$scope begin fec_gen[19] $end
$upscope $end
$scope begin fec_gen[20] $end
$upscope $end
$scope begin fec_gen[21] $end
$upscope $end
$scope begin fec_gen[22] $end
$upscope $end
$scope begin fec_gen[23] $end
$upscope $end
$scope begin fec_gen[24] $end
$upscope $end
$scope begin fec_gen[25] $end
$upscope $end
$scope begin fec_gen[26] $end
$upscope $end
$scope begin fec_gen[27] $end
$upscope $end
$scope begin fec_gen[28] $end
$upscope $end
$scope begin fec_gen[29] $end
$upscope $end
$scope begin fec_gen[30] $end
$upscope $end
$scope begin fec_gen[31] $end
$upscope $end
$scope begin fec_gen[32] $end
$upscope $end
$scope begin fec_gen[33] $end
$upscope $end
$scope begin fec_gen[34] $end
$upscope $end
$scope begin fec_gen[35] $end
$upscope $end
$scope begin fec_gen[36] $end
$upscope $end
$scope begin fec_gen[37] $end
$upscope $end
$scope begin fec_gen[38] $end
$upscope $end
$scope begin fec_gen[39] $end
$upscope $end
$scope begin fec_gen[40] $end
$upscope $end
$scope begin fec_gen[41] $end
$upscope $end
$scope begin fec_gen[42] $end
$upscope $end
$scope begin fec_gen[43] $end
$upscope $end
$scope begin fec_gen[44] $end
$upscope $end
$scope begin fec_gen[45] $end
$upscope $end
$scope begin fec_gen[46] $end
$upscope $end
$scope begin fec_gen[47] $end
$upscope $end
$scope begin fec_gen[48] $end
$upscope $end
$scope begin fec_gen[49] $end
$upscope $end
$scope begin fec_gen[50] $end
$upscope $end
$scope begin fec_gen[51] $end
$upscope $end
$scope begin fec_gen[52] $end
$upscope $end
$scope begin fec_gen[53] $end
$upscope $end
$scope begin fec_gen[54] $end
$upscope $end
$scope begin fec_gen[55] $end
$upscope $end
$scope begin fec_gen[56] $end
$upscope $end
$scope begin fec_gen[57] $end
$upscope $end
$scope begin fec_gen[58] $end
$upscope $end
$scope begin fec_gen[59] $end
$upscope $end
$scope begin fec_gen[60] $end
$upscope $end
$scope begin fec_gen[61] $end
$upscope $end
$scope begin fec_gen[62] $end
$upscope $end
$scope begin fec_gen[63] $end
$upscope $end
$scope begin fec_gen[64] $end
$upscope $end
$scope begin fec_gen[65] $end
$upscope $end
$scope begin fec_gen[66] $end
$upscope $end
$scope begin fec_gen[67] $end
$upscope $end
$scope begin fec_gen[68] $end
$upscope $end
$scope begin fec_gen[69] $end
$upscope $end
$scope begin fec_gen[70] $end
$upscope $end
$scope begin fec_gen[71] $end
$upscope $end
$scope begin fec_gen[72] $end
$upscope $end
$scope begin fec_gen[73] $end
$upscope $end
$scope begin fec_gen[74] $end
$upscope $end
$scope begin fec_gen[75] $end
$upscope $end
$scope begin fec_gen[76] $end
$upscope $end
$scope begin fec_gen[77] $end
$upscope $end
$scope begin fec_gen[78] $end
$upscope $end
$scope begin fec_gen[79] $end
$upscope $end
$scope begin fec_gen[80] $end
$upscope $end
$scope begin fec_gen[81] $end
$upscope $end
$scope begin fec_gen[82] $end
$upscope $end
$scope begin fec_gen[83] $end
$upscope $end
$scope begin fec_gen[84] $end
$upscope $end
$scope begin fec_gen[85] $end
$upscope $end
$scope begin fec_gen[86] $end
$upscope $end
$scope begin fec_gen[87] $end
$upscope $end
$scope begin fec_gen[88] $end
$upscope $end
$scope begin fec_gen[89] $end
$upscope $end
$scope begin fec_gen[90] $end
$upscope $end
$scope begin fec_gen[91] $end
$upscope $end
$scope begin fec_gen[92] $end
$upscope $end
$scope begin fec_gen[93] $end
$upscope $end
$scope begin fec_gen[94] $end
$upscope $end
$scope begin fec_gen[95] $end
$upscope $end
$scope begin fec_rev_gen[3] $end
$upscope $end
$scope begin fec_rev_gen[4] $end
$upscope $end
$scope begin fec_rev_gen[5] $end
$upscope $end
$scope begin fec_rev_gen[6] $end
$upscope $end
$scope begin fec_rev_gen[7] $end
$upscope $end
$scope begin fec_rev_gen[8] $end
$upscope $end
$scope begin fec_rev_gen[9] $end
$upscope $end
$scope begin fec_rev_gen[10] $end
$upscope $end
$scope begin fec_rev_gen[11] $end
$upscope $end
$scope begin fec_rev_gen[12] $end
$upscope $end
$scope begin fec_rev_gen[13] $end
$upscope $end
$scope begin fec_rev_gen[14] $end
$upscope $end
$scope begin fec_rev_gen[15] $end
$upscope $end
$scope begin fec_rev_gen[16] $end
$upscope $end
$scope begin fec_rev_gen[17] $end
$upscope $end
$scope begin fec_rev_gen[18] $end
$upscope $end
$scope begin fec_rev_gen[19] $end
$upscope $end
$scope begin fec_rev_gen[20] $end
$upscope $end
$scope begin fec_rev_gen[21] $end
$upscope $end
$scope begin fec_rev_gen[22] $end
$upscope $end
$scope begin fec_rev_gen[23] $end
$upscope $end
$scope begin fec_rev_gen[24] $end
$upscope $end
$scope begin fec_rev_gen[25] $end
$upscope $end
$scope begin fec_rev_gen[26] $end
$upscope $end
$scope begin fec_rev_gen[27] $end
$upscope $end
$scope begin fec_rev_gen[28] $end
$upscope $end
$scope begin fec_rev_gen[29] $end
$upscope $end
$scope begin fec_rev_gen[30] $end
$upscope $end
$scope begin fec_rev_gen[31] $end
$upscope $end
$scope begin fec_rev_gen[32] $end
$upscope $end
$scope begin fec_rev_gen[33] $end
$upscope $end
$scope begin fec_rev_gen[34] $end
$upscope $end
$scope begin fec_rev_gen[35] $end
$upscope $end
$scope begin fec_rev_gen[36] $end
$upscope $end
$scope begin fec_rev_gen[37] $end
$upscope $end
$scope begin fec_rev_gen[38] $end
$upscope $end
$scope begin fec_rev_gen[39] $end
$upscope $end
$scope begin fec_rev_gen[40] $end
$upscope $end
$scope begin fec_rev_gen[41] $end
$upscope $end
$scope begin fec_rev_gen[42] $end
$upscope $end
$scope begin fec_rev_gen[43] $end
$upscope $end
$scope begin fec_rev_gen[44] $end
$upscope $end
$scope begin fec_rev_gen[45] $end
$upscope $end
$scope begin fec_rev_gen[46] $end
$upscope $end
$scope begin fec_rev_gen[47] $end
$upscope $end
$scope begin input_rev[0] $end
$upscope $end
$scope begin input_rev[1] $end
$upscope $end
$scope begin input_rev[2] $end
$upscope $end
$scope begin input_rev[3] $end
$upscope $end
$scope begin input_rev[4] $end
$upscope $end
$scope begin input_rev[5] $end
$upscope $end
$scope begin input_rev[6] $end
$upscope $end
$scope begin input_rev[7] $end
$upscope $end
$scope begin input_rev[8] $end
$upscope $end
$scope begin input_rev[9] $end
$upscope $end
$scope begin input_rev[10] $end
$upscope $end
$scope begin input_rev[11] $end
$upscope $end
$scope begin input_rev[12] $end
$upscope $end
$scope begin input_rev[13] $end
$upscope $end
$scope begin input_rev[14] $end
$upscope $end
$scope begin input_rev[15] $end
$upscope $end
$scope begin input_rev[16] $end
$upscope $end
$scope begin input_rev[17] $end
$upscope $end
$scope begin input_rev[18] $end
$upscope $end
$scope begin input_rev[19] $end
$upscope $end
$scope begin input_rev[20] $end
$upscope $end
$scope begin input_rev[21] $end
$upscope $end
$scope begin input_rev[22] $end
$upscope $end
$scope begin input_rev[23] $end
$upscope $end
$scope begin input_rev[24] $end
$upscope $end
$scope begin input_rev[25] $end
$upscope $end
$scope begin input_rev[26] $end
$upscope $end
$scope begin input_rev[27] $end
$upscope $end
$scope begin input_rev[28] $end
$upscope $end
$scope begin input_rev[29] $end
$upscope $end
$scope begin input_rev[30] $end
$upscope $end
$scope begin input_rev[31] $end
$upscope $end
$scope begin input_rev[32] $end
$upscope $end
$scope begin input_rev[33] $end
$upscope $end
$scope begin input_rev[34] $end
$upscope $end
$scope begin input_rev[35] $end
$upscope $end
$scope begin input_rev[36] $end
$upscope $end
$scope begin input_rev[37] $end
$upscope $end
$scope begin input_rev[38] $end
$upscope $end
$scope begin input_rev[39] $end
$upscope $end
$scope begin input_rev[40] $end
$upscope $end
$scope begin input_rev[41] $end
$upscope $end
$scope begin input_rev[42] $end
$upscope $end
$scope begin input_rev[43] $end
$upscope $end
$scope begin input_rev[44] $end
$upscope $end
$scope begin input_rev[45] $end
$upscope $end
$scope begin input_rev[46] $end
$upscope $end
$scope begin input_rev[47] $end
$upscope $end
$upscope $end
$upscope $end
$upscope $end
$enddefinitions $end
#0
$dumpvars
b111111111111111100000000000000000000000000000000 ;
b11100110101010101010101010101010 :
b10101010101010101010101011001110000000000000000000000000000000000000000000000000000000000000000 9
b1111111111111111 8
07
b1111111111111111 6
b11111 5
b100000 4
b0 3
b0 2
b1111111111111111 1
b1111111111111111 0
b11100110101010101010101010101010 /
b1110011000000110010000100001000000100010001000100011000000100000001000000110010000100100001000100010001000100010111000000110010000001110001000100000101000100001001000001000110 .
b1110011000000110010000100001000000100010001000100011000000100000001000000110010000100100001000100010001000100010111000000110010000001110001000100000101000100001001000001000110 -
bx ,
0+
0*
0)
b11000000010000001000000011 (
0'
0&
b0 %
0$
b11100110101010101010101010101010 #
b1110011000000110010000100001000000100010001000100011000000100000001000000110010000100100001000100010001000100010111000000110010000001110001000100000101000100001001000001000110 "
b111010001100000000110111110000001101111100000000111010000010100011000000111001011110 !
$end
#5
b1 %
b1 2
1'
#7
1)
#10
0'
#12
0)
#15
b10 %
b10 2
1'
#17
1)
#20
0'
#22
0)
#25
b11 %
b11 2
1'
#27
1)
#30
0'
#32
0)
#35
b100 %
b100 2
1'
#37
1)
#40
0'
#42
0)
#45
b101 %
b101 2
1'
#47
1)
#50
0'
#52
0)
#55
b110 %
b110 2
1'
#57
1)
#60
0'
#62
0)
#65
b111 %
b111 2
1'
#67
1)
#70
0'
#72
0)
#75
b1000 %
b1000 2
1'
#77
1)
#80
0'
#82
0)
#85
b1001 %
b1001 2
1'
#87
1)
#90
0'
#92
0)
#95
b1010 %
b1010 2
1'
#97
1)
#100
b0 %
b0 2
0'
1+
#102
0)
#105
17
1'
#107
1)
#110
0'
1+
#112
0)
#115
1'
#117
1)
#120
0'
0+
#122
0)
#125
b111001101010101010101010011101 #
b111001101010101010101010011101 /
b111001101010101010101010011101 :
b101110010101010101010101100111000000000000000000000000000000000000000000000000000000000000000000 9
b110111111111111000000000000000000000000000000000 ;
b100001 4
b100000 5
b111111111111011 0
b111111111111011 8
b111111111111011 1
b111111111111011 6
b1 %
b1 2
1'
b0 ,
#127
b1 ,
b110000000100000010000000110 (
1)
#130
0'
#132
0)
#135
b11100110101010101010101001110110 #
b11100110101010101010101001110110 /
b11100110101010101010101001110110 :
b11011100101010101010101011001110000000000000000000000000000000000000000000000000000000000000000 9
b11011111111111100000000000000000000000000000000 ;
b100010 4
b100001 5
b1111111111110110 0
b1111111111110110 8
b1111111111110110 1
b1111111111110110 6
b10 %
b10 2
1'
#137
b10 ,
b1100000001000000100000001100 (
1)
#140
0'
#142
0)
#145
b111001101010101010100111101100 #
b111001101010101010100111101100 /
b111001101010101010100111101100 :
b1101111001010101010101100111000000000000000000000000000000000000000000000000000000000000000000 9
b100101111111111000000000000000000000000000000000 ;
b100011 4
b100010 5
b111111111101001 0
b111111111101001 8
b111111111101001 1
b111111111101001 6
b11 %
b11 2
1'
#147
b11 ,
b11000000010000001000000011000 (
1)
#150
0'
#152
0)
#155
b11100110101010101010011110110001 #
b11100110101010101010011110110001 /
b11100110101010101010011110110001 :
b100011011110010101010101011001110000000000000000000000000000000000000000000000000000000000000000 9
b10010111111111100000000000000000000000000000000 ;
b100100 4
b100011 5
b1111111111010010 0
b1111111111010010 8
b1111111111010010 1
b1111111111010010 6
b100 %
b100 2
1'
#157
b100 ,
b110000000100000010000000110000 (
1)
#160
0'
#162
0)
#165
b111001101010101001111011110011 #
b111001101010101001111011110011 /
b111001101010101001111011110011 :
b110011110111100101010101100111000000000000000000000000000000000000000000000000000000000000000000 9
b100001011111111000000000000000000000000000000000 ;
b100101 4
b100100 5
b111111110100001 0
b111111110100001 8
b111111110100001 1
b111111110100001 6
b101 %
b101 2
1'
#167
b101 ,
b1100000001000000100000001100000 (
1)
#170
0'
#172
0)
#175
b11100110101010100111101111001101 #
b11100110101010100111101111001101 /
b11100110101010100111101111001101 :
b101100111101111001010101011001110000000000000000000000000000000000000000000000000000000000000000 9
b10000101111111100000000000000000000000000000000 ;
b100110 4
b100101 5
b1111111101000010 0
b1111111101000010 8
b1111111101000010 1
b1111111101000010 6
b110 %
b110 2
1'
#177
1*
b110 ,
b11000000010000001000000011000000 (
1)
#180
0'
#182
0)
#185
b1110011010101010011110111100110111 #
b1110011010101010011110111100110111 /
b1110011010101010011110111100110111 :
b111011001111011110010101010110011100000000000000000000000000000000000000000000000000000000000000 9
b1000010111111110000000000000000000000000000000 ;
b100111 4
b100110 5
b1111111010000100 1
b1111111010000100 6
b11111111010000100 0
b11111111010000100 8
b1 3
b111 %
b111 2
1'
#187
b111 ,
b10000000100000010000000110000000 (
1)
#190
0'
#192
0)
#195
b111001101010101001111011110011011111 #
b111001101010101001111011110011011111 /
b111001101010101001111011110011011111 :
b111110110011110111100101010101100111000000000000000000000000000000000000000000000000000000000000 9
b100001011111111000000000000000000000000000000 ;
b101000 4
b100111 5
b1111110100001000 1
b1111110100001000 6
b111111110100001000 0
b111111110100001000 8
b11 3
b1000 %
b1000 2
1'
#197
0*
b1000 ,
b1000000100000001100000000 (
1)
#200
0'
#202
0)
#205
b11101000001001100111101111001101001000 #
b11101000001001100111101111001101001000 /
b11101000001001100111101111001101001000 :
b100101100111101111001100100000101110000000000000000000000000000000000000000000000000000000000 9
b101010000101111001100000000000000000000000000000 ;
b101001 4
b101000 5
b111101000010101 1
b111101000010101 6
b1100111101000010101 0
b1100111101000010101 8
b110 3
b1001 %
b1001 2
1'
#207
b1001 ,
b10000001000000011000000000 (
1)
#210
0'
#212
0)
#215
b1110100000100110011110111100110100100010 #
b1110100000100110011110111100110100100010 /
b1110100000100110011110111100110100100010 :
b10001001011001111011110011001000001011100000000000000000000000000000000000000000000000000000000 9
b10101000010111100110000000000000000000000000000 ;
b101010 4
b101001 5
b1111010000101010 1
b1111010000101010 6
b11001111010000101010 0
b11001111010000101010 8
b1100 3
b1010 %
b1010 2
1'
#217
b1010 ,
b100000010000000110000000000 (
1)
#220
0'
#222
0)
#225
b111010001100111010111011110011010010111111 #
b111010001100111010111011110011010010111111 /
b111010001100111010111011110011010010111111 :
b111111010010110011110111010111001100010111000000000000000000000000000000000000000000000000000000 9
b100010100001011000011000000000000000000000000000 ;
b101011 4
b101010 5
b110100001010001 1
b110100001010001 6
b110000110100001010001 0
b110000110100001010001 8
b11000 3
b1011 %
b1011 2
1'
#227
b1011 ,
b1000000100000001100000000000 (
1)
#230
0'
#232
0)
#235
b11101000110011101011101111001101001011111101 #
b11101000110011101011101111001101001011111101 /
b11101000110011101011101111001101001011111101 :
b101111110100101100111101110101110011000101110000000000000000000000000000000000000000000000000000 9
b10001010000101100001100000000000000000000000000 ;
b101100 4
b101011 5
b1101000010100010 1
b1101000010100010 6
b1100001101000010100010 0
b1100001101000010100010 8
b110000 3
b1100 %
b1100 2
1'
#237
b1100 ,
b10000001000000011000000000000 (
1)
#240
0'
#242
0)
#245
b1110100011000000001101111100110100101111000011 #
b1110100011000000001101111100110100101111000011 /
b1110100011000000001101111100110100101111000011 :
b110000111101001011001111101100000000110001011100000000000000000000000000000000000000000000000000 9
b100000101000010000000110000000000000000000000000 ;
b101101 4
b101100 5
b10000101000001 1
b10000101000001 6
b11000000010000101000001 0
b11000000010000101000001 8
b1100000 3
b1101 %
b1101 2
1'
#247
b1101 ,
b100000010000000110000000000000 (
1)
#250
0'
#252
0)
#255
b111010001100000000110111110011010010111100001101 #
b111010001100000000110111110011010010111100001101 /
b111010001100000000110111110011010010111100001101 :
b101100001111010010110011111011000000001100010111000000000000000000000000000000000000000000000000 9
b10000010100001000000011000000000000000000000000 ;
b101110 4
b101101 5
b100001010000010 1
b100001010000010 6
b110000000100001010000010 0
b110000000100001010000010 8
b11000000 3
b1110 %
b1110 2
1'
#257
b1110 ,
b1000000100000001100000000000000 (
1)
#260
0'
#262
0)
#265
b11101000110000000011011111001101001011110000110111 #
b11101000110000000011011111001101001011110000110111 /
b11101000110000000011011111001101001011110000110111 :
b111011000011110100101100111110110000000011000101110000000000000000000000000000000000000000000000 9
b1000001010000100000001100000000000000000000000 ;
b101111 4
b101110 5
b1000010100000100 1
b1000010100000100 6
b1100000001000010100000100 0
b1100000001000010100000100 8
b110000000 3
b1111 %
b1111 2
1'
#267
1*
b1111 ,
b10000001000000011000000000000000 (
1)
#270
0'
#272
0)
#275
b1110100011000000001101111100110100101111000011011111 #
b1110100011000000001101111100110100101111000011011111 /
b1110100011000000001101111100110100101111000011011111 :
b111110110000111101001011001111101100000000110001011100000000000000000000000000000000000000000000 9
b100000101000010000000110000000000000000000000 ;
b110000 4
b101111 5
b101000001000 1
b101000001000 6
b11000000010000101000001000 0
b11000000010000101000001000 8
b1100000001 3
b10000 %
b10000 2
1'
#277
0*
b10000 ,
b10000000110000000000000000 (
1)
#280
0'
#282
0)
#285
b111010001100000000110111110011010010111100001101111100 #
b111010001100000000110111110011010010111100001101111100 /
b111010001100000000110111110011010010111100001101111100 :
b1111101100001111010010110011111011000000001100010111000000000000000000000000000000000000000000 9
b10000010100001000000011000000000000000000000 ;
b110001 4
b110000 5
b1010000010000 1
b1010000010000 6
b110000000100001010000010000 0
b110000000100001010000010000 8
b11000000010 3
b10001 %
b10001 2
1'
#287
b10001 ,
b100000001100000000000000000 (
1)
#290
0'
#292
0)
#295
b11101000110000000011011111001101001011110000110111110000 #
b11101000110000000011011111001101001011110000110111110000 /
b11101000110000000011011111001101001011110000110111110000 :
b11111011000011110100101100111110110000000011000101110000000000000000000000000000000000000000 9
b1000001010000100000001100000000000000000000 ;
b110010 4
b110001 5
b10100000100000 1
b10100000100000 6
b1100000001000010100000100000 0
b1100000001000010100000100000 8
b110000000100 3
b10010 %
b10010 2
1'
#297
b10010 ,
b1000000011000000000000000000 (
1)
#300
0'
#302
0)
#305
b1110100011000000001101111100110100101111000011011111000000 #
b1110100011000000001101111100110100101111000011011111000000 /
b1110100011000000001101111100110100101111000011011111000000 :
b111110110000111101001011001111101100000000110001011100000000000000000000000000000000000000 9
b100000101000010000000110000000000000000000 ;
b110011 4
b110010 5
b101000001000000 1
b101000001000000 6
b11000000010000101000001000000 0
b11000000010000101000001000000 8
b1100000001000 3
b10011 %
b10011 2
1'
#307
b10011 ,
b10000000110000000000000000000 (
1)
#310
0'
#312
0)
#315
b111010001100000000110111110011010010111100001101111100000000 #
b111010001100000000110111110011010010111100001101111100000000 /
b111010001100000000110111110011010010111100001101111100000000 :
b1111101100001111010010110011111011000000001100010111000000000000000000000000000000000000 9
b10000010100001000000011000000000000000000 ;
b110100 4
b110011 5
b1010000010000000 1
b1010000010000000 6
b110000000100001010000010000000 0
b110000000100001010000010000000 8
b11000000010000 3
b10100 %
b10100 2
1'
#317
b10100 ,
b100000001100000000000000000000 (
1)
#320
0'
#322
0)
#325
b11101000110000000011011111000011101000110000110111110000110100 #
b11101000110000000011011111000011101000110000110111110000110100 /
b11101000110000000011011111000011101000110000110111110000110100 :
b1011000011111011000011000101110000111110110000000011000101110000000000000000000000000000000000 9
b101000001000001100000100000001100000000000000000 ;
b110101 4
b110100 5
b1100000100000101 1
b1100000100000101 6
b1100000001000001100000100000101 0
b1100000001000001100000100000101 8
b110000000100000 3
b10101 %
b10101 2
1'
#327
b10101 ,
b1000000011000000000000000000000 (
1)
#330
0'
#332
0)
#335
b1110100011000000001101111100000000000000000011011111000011100110 #
b1110100011000000001101111100000000000000000011011111000011100110 /
b1110100011000000001101111100000000000000000011011111000011100110 :
b11001110000111110110000000000000000001111101100000000110001011100000000000000000000000000000000 9
b111100000100000000000010000000110000000000000000 ;
b110110 4
b110101 5
b1000001111 1
b1000001111 6
b11000000010000000000001000001111 0
b11000000010000000000001000001111 8
b1100000001000000 3
b10110 %
b10110 2
1'
#337
1*
b10110 ,
b10000000110000000000000000000000 (
1)
#340
0'
#342
0)
#345
b111010001100000000110111110000001110100011001101111100001110101101 #
b111010001100000000110111110000001110100011001101111100001110101101 /
b111010001100000000110111110000001110100011001101111100001110101101 :
b101101011100001111101100110001011100000011111011000000001100010111000000000000000000000000000000 9
b110110000010000110000001000000011000000000000000 ;
b110111 4
b110110 5
b1000010000011011 1
b1000010000011011 6
b110000000100000011000010000011011 0
b110000000100000011000010000011011 8
b11000000010000001 3
b10111 %
b10111 2
1'
#347
0*
b10111 ,
b1100000000000000000000000 (
1)
#350
0'
#352
0)
#355
b11101000110000000011011111000000110100101111110111110000111010000010 #
b11101000110000000011011111000000110100101111110111110000111010000010 /
b11101000110000000011011111000000110100101111110111110000111010000010 :
b10000010111000011111011111101001011000000111110110000000011000101110000000000000000000000000000 9
b110011000001000101000000100000001100000000000000 ;
b111000 4
b110111 5
b1000100000110011 1
b1000100000110011 6
b1100000001000000101000100000110011 0
b1100000001000000101000100000110011 8
b110000000100000010 3
b11000 %
b11000 2
1'
#357
b11000 ,
b11000000000000000000000000 (
1)
#360
0'
#362
0)
#365
b1110100011000000001101111100000011011100011100011111000011101000111110 #
b1110100011000000001101111100000011011100011100011111000011101000111110 /
b1110100011000000001101111100000011011100011100011111000011101000111110 :
b11111000101110000111110001110001110110000001111101100000000110001011100000000000000000000000000 9
b110001100000100100100000010000000110000000000000 ;
b111001 4
b111000 5
b1001000001100011 1
b1001000001100011 6
b11000000010000001001001000001100011 0
b11000000010000001001001000001100011 8
b1100000001000000100 3
b11001 %
b11001 2
1'
#367
b11001 ,
b110000000000000000000000000 (
1)
#370
0'
#372
0)
#375
b111010001100000000110111110000001101111111010010111100001110100011001110 #
b111010001100000000110111110000001101111111010010111100001110100011001110 /
b111010001100000000110111110000001101111111010010111100001110100011001110 :
b11100110001011100001111010010111111101100000011111011000000001100010111000000000000000000000000 9
b110000110000010100010000001000000011000000000000 ;
b111010 4
b111001 5
b1010000011000011 1
b1010000011000011 6
b110000000100000010001010000011000011 0
b110000000100000010001010000011000011 8
b11000000010000001000 3
b11010 %
b11010 2
1'
#377
b11010 ,
b1100000000000000000000000000 (
1)
#380
0'
