6111work/Labs/Lab4/Lab4/Lab4.srcs/sources_1/new/alarm_fsm.v
`timescale 1ns / 1ps
//////////////////////////////////////////////////////////////////////////////////
// Company:  ilovesystemverilog
// Engineer: magson gao
// 
// Create Date: 10/02/2018 04:27:46 PM
// Design Name: whylifewhy
// Module Name: alarm_fsm
// Project Name: lab4wouldbenefitfromsomesystemverilogmagic
// Target Devices: nexys somethingorother
// Tool Versions: bad
// Description: imisssystemverilog
// 
// Dependencies: brain and soul
// 
// Revision: still broken
// Revision 0.01 - File Created
// Additional Comments: well done
// 
//////////////////////////////////////////////////////////////////////////////////


module alarm_fsm( 
                    clk_in,
                    clk_1Hz_in,
                    ignition_in, 
                    driver_door_in, 
                    passenger_door_in, 
                    program_in, 
                    expired_in, 
                    siren_out,
                    start_time_out,
                    interval_out,
                    status_out 
                );
    localparam DISARMED    = 0;
    localparam ARMED       = 1;
    localparam TRIGGERED   = 2;
    localparam SOUND_ALARM = 3;
    
    
    localparam SEL_ARM_DELAY       = 2'b00;
    localparam SEL_DRIVER_DELAY    = 2'b01;
    localparam SEL_PASSENGER_DELAY = 2'b10;
    localparam SEL_ALARM_ON        = 2'b11;
    
    input clk_in;
    input clk_1Hz_in;
    input ignition_in;
    input driver_door_in;
    input passenger_door_in;
    input program_in;
    input expired_in;
    
    output siren_out;
    output status_out;
    output start_time_out;
    output [1:0] interval_out;
    
    reg status_out = 1'b0;   
    reg [1:0] state = DISARMED;
    reg [1:0] interval_out = SEL_PASSENGER_DELAY;
    reg start_time_out;
    reg driver_leaving = 1'b0;
    
    always @(posedge clk_1Hz_in or posedge program_in)
    begin    
        if (program_in | (state == ARMED))
        begin
            status_out <= ~status_out;
        end
        else if ((state == TRIGGERED) | (state == SOUND_ALARM))
        begin
            status_out <= 1'b1;
        end
        else // if (status == DISARMED)
        begin
            status_out <= 1'b0;
        end
    end

    assign siren_out = set_siren(program_in, state);
    
    always @(posedge clk_in or posedge program_in)
    begin
        if (program_in | (state == ARMED))
        begin
            if (ignition_in)
            begin
                state <= DISARMED;
                start_time_out <= 1'b0;
            end
            else if (~program_in)
            begin
                if (driver_door_in)
                begin
                    start_time_out <= 1'b1;
                    interval_out <= SEL_DRIVER_DELAY;
                    state <= TRIGGERED;
                end
                else if (passenger_door_in)
                begin
                    start_time_out <= 1'b1; 
                    interval_out <= SEL_PASSENGER_DELAY;
                    state <= TRIGGERED;
                end
            end
            else 
            begin
                start_time_out <= 1'b0;
                state <= ARMED;    
            end
        end
        else if (state == TRIGGERED)
        begin
            if (ignition_in)
            begin
                start_time_out <= 1'b0;
                state <= DISARMED;
            end
            else if (expired_in)
            begin
                start_time_out <= 1'b1;
                state <= SOUND_ALARM;
                interval_out <= SEL_ALARM_ON;
            end
            else 
            begin
                start_time_out <= 1'b0;
            end
        end
        else if (state == SOUND_ALARM)
        begin
            if (ignition_in | (expired_in & (~(driver_door_in | passenger_door_in))))
            begin
                state <= DISARMED;
                start_time_out <= 1'b0;
            end
            else 
            begin
                start_time_out <= 1'b0;    
            end
        end
        else if (state == DISARMED)
        begin
            if ((~ignition_in) & driver_door_in)
            begin
                start_time_out <= 1'b0;
                driver_leaving <= 1'b1;
            end
            else if (driver_leaving & (~driver_door_in))
            begin
                driver_leaving <= 1'b0;
                start_time_out <= 1'b1;
                interval_out   <= SEL_ARM_DELAY;                
            end
            else if (expired_in)
            begin
                start_time_out <= 1'b0;
                state <= ARMED;
            end
        end
    end

    function set_siren;
    input       program_in;
    input [1:0] state;
    begin
        if (program_in)
        begin
            set_siren = 1'b0;
        end
        else if ( state == SOUND_ALARM )
        begin
            set_siren = 1'b1;
        end
        else
        begin
            set_siren = 1'b0;
        end 
    end
    endfunction       
endmodule

6111work/Labs/Lab4/Lab4/Lab4.srcs/sources_1/new/alarm_fsm_tb.v
module alarm_fsm_tb;
	reg     clk             = 1'b0;
	reg     ignition        = 1'b0;
	reg     driver_door     = 1'b0;
	reg     passenger_door  = 1'b0;
	reg     program         = 1'b1;
	reg     expired         = 1'b0;


	wire       siren;
	wire       start_time;
	wire [1:0] interval;
	wire       status;

	alarm_fsm af1(
					.clk_in(clk),
					.clk_1Hz_in(clk),
					.ignition_in(ignition),
					.driver_door_in(driver_door),
					.passenger_door_in(passenger_door),
					.program_in(program),
					.expired_in(expired),
					.siren_out(siren),
					.start_time_out(start_time),
					.interval_out(interval),
					.status_out(status)
					);
	initial
	begin
		$dumpfile("alarm_test.vcd");
		$dumpvars(0, alarm_fsm_tb);
		reset_fsm;
		#50;
		ignition = 1'b1;

		reset_fsm;

		#10; // expect instant transition
		ignition = 1'b0;
		
		reset_fsm;

		passenger_door = 1'b1;
		
		#10;

		passenger_door = 1'b0;

		reset_fsm;

		driver_door = 1'b1;

		#10;

		driver_door = 1'b0;

		reset_fsm;

		#10;

		ignition = 1'b1;

		#10;
		ignition = 1'b0;
		driver_door = 1'b1;
		#10;
		// should do nothing
		passenger_door = 1'b1;
		#10;
		passenger_door = 1'b0;
		driver_door = 1'b0;
		#10;
		expired = 1'b1;
		#100;
		expired = 1'b0;
		driver_door = 1'b1;
		#20;
		ignition = 1'b1;
		#10;
		ignition = 1'b0;

		// expect instant transition
		reset_fsm;

		#20;
		// does nothing
		passenger_door = 1'b1;

		#10;
		expired = 1'b1;
		#20;
		passenger_door = 1'b0;
		driver_door    = 1'b0;
		expired     = 1'b0;

		reset_fsm;

		passenger_door = 1'b1;

		// does nothing
		driver_door = 1'b1;
		#10;
		expired = 1'b1;
		#5;
		expired = 1'b0;
		#10;
		expired = 1'b1;
		#20;
		driver_door = 1'b0;
		#10;
		passenger_door = 1'b0;
		#10;
		reset_fsm;

		passenger_door = 1'b1;
		#10;
		// does nothing
		driver_door = 1'b1;
		#10;
		expired = 1'b1;
		#5;
		expired = 1'b0;
		#10;
		ignition = 1'b1;
		#20;
		$finish;


	end

	always #5 clk = ~clk;

	task reset_fsm;
	begin
		#10;
		program = 1'b1;
		expired = 1'b0;
		#10;
		program = 1'b0;
		#10;
	end
	endtask
endmodule

6111work/Labs/Lab4/Lab4/Lab4.srcs/sources_1/new/alarm_test.vcd
$date
	Wed Oct 10 09:01:41 2018
$end
$version
	Icarus Verilog
$end
$timescale
	1ps
$end
$scope module alarm_fsm_tb $end
$var wire 1 ! status $end
$var wire 1 " start_time $end
$var wire 1 # siren $end
$var wire 2 $ interval [1:0] $end
$var reg 1 % clk $end
$var reg 1 & driver_door $end
$var reg 1 ' expired $end
$var reg 1 ( ignition $end
$var reg 1 ) passenger_door $end
$var reg 1 * program $end
$scope module af1 $end
$var wire 1 % clk_1Hz_in $end
$var wire 1 % clk_in $end
$var wire 1 & driver_door_in $end
$var wire 1 ' expired_in $end
$var wire 1 ( ignition_in $end
$var wire 1 ) passenger_door_in $end
$var wire 1 * program_in $end
$var wire 1 # siren_out $end
$var reg 1 + driver_leaving $end
$var reg 2 , interval_out [1:0] $end
$var reg 1 " start_time_out $end
$var reg 2 - state [1:0] $end
$var reg 1 ! status_out $end
$scope function set_siren $end
$var reg 1 . program_in $end
$var reg 1 / set_siren $end
$var reg 2 0 state [1:0] $end
$upscope $end
$upscope $end
$scope task reset_fsm $end
$upscope $end
$upscope $end
$enddefinitions $end
#0
$dumpvars
b1 0
0/
1.
b1 -
b10 ,
0+
1*
0)
0(
0'
0&
0%
b10 $
0#
0"
1!
$end
#5000000000000
0!
1%
#10000000000000
0%
#15000000000000
1!
1%
#20000000000000
0.
0%
0*
#25000000000000
0!
1%
#30000000000000
0%
#35000000000000
1!
1%
#40000000000000
0%
#45000000000000
0!
1%
#50000000000000
0%
#55000000000000
1!
1%
#60000000000000
0%
#65000000000000
0!
1%
#70000000000000
0%
#75000000000000
1!
1%
#80000000000000
0%
1(
#85000000000000
b0 0
b0 -
0!
1%
#90000000000000
1!
1.
0%
1*
#95000000000000
0!
1%
#100000000000000
0.
0%
0*
#105000000000000
1%
#110000000000000
0%
#115000000000000
1%
#120000000000000
0%
0(
#125000000000000
1%
#130000000000000
b1 0
b1 -
1!
1.
0%
1*
#135000000000000
0!
1%
#140000000000000
0.
0%
0*
#145000000000000
1!
1%
#150000000000000
0%
1)
#155000000000000
b10 0
0!
b10 -
1"
1%
#160000000000000
0%
0)
#165000000000000
0"
1!
1%
#170000000000000
b1 0
0!
b1 -
1.
0%
1*
#175000000000000
1!
1%
#180000000000000
0.
0%
0*
#185000000000000
0!
1%
#190000000000000
0%
1&
#195000000000000
b10 0
b10 -
b1 $
b1 ,
1"
1!
1%
#200000000000000
0%
0&
#205000000000000
0"
1%
#210000000000000
b1 0
b1 -
0!
1.
0%
1*
#215000000000000
1!
1%
#220000000000000
0.
0%
0*
#225000000000000
0!
1%
#230000000000000
0%
#235000000000000
1!
1%
#240000000000000
0%
1(
#245000000000000
b0 0
b0 -
0!
1%
#250000000000000
0%
1&
0(
#255000000000000
1+
1%
#260000000000000
0%
1)
#265000000000000
1%
#270000000000000
0%
0&
0)
#275000000000000
b0 $
b0 ,
1"
0+
1%
#280000000000000
0%
1'
#285000000000000
b1 0
b1 -
0"
1%
#290000000000000
0%
#295000000000000
1!
1%
#300000000000000
0%
#305000000000000
0!
1%
#310000000000000
0%
#315000000000000
1!
1%
#320000000000000
0%
#325000000000000
0!
1%
#330000000000000
0%
#335000000000000
1!
1%
#340000000000000
0%
#345000000000000
0!
1%
#350000000000000
0%
#355000000000000
1!
1%
#360000000000000
0%
#365000000000000
0!
1%
#370000000000000
0%
#375000000000000
1!
1%
#380000000000000
0%
1&
0'
#385000000000000
b10 0
b10 -
b1 $
b1 ,
1"
0!
1%
#390000000000000
0%
#395000000000000
1!
0"
1%
#400000000000000
0%
1(
#405000000000000
b0 0
b0 -
1%
#410000000000000
0%
0(
#415000000000000
0!
1+
1%
#420000000000000
b1 0
b1 -
1!
1.
0%
1*
#425000000000000
0!
1%
#430000000000000
0.
0%
0*
#435000000000000
b10 0
b10 -
1"
1!
1%
#440000000000000
0%
#445000000000000
0"
1%
#450000000000000
0%
#455000000000000
1%
#460000000000000
0%
1)
#465000000000000
1%
#470000000000000
0%
1'
#475000000000000
1#
1/
b11 0
b11 $
b11 ,
b11 -
1"
1%
#480000000000000
0%
#485000000000000
0"
1%
#490000000000000
0%
0'
0&
0)
#495000000000000
1%
#500000000000000
b1 0
0!
b1 -
0#
0/
1.
0%
1*
#505000000000000
1!
1%
#510000000000000
0.
0%
0*
#515000000000000
0!
1%
#520000000000000
0%
1&
1)
#525000000000000
b10 0
b10 -
b1 $
b1 ,
1"
1!
1%
#530000000000000
0%
1'
#535000000000000
0"
1%
0'
#540000000000000
0%
#545000000000000
1#
1/
b11 0
b11 $
b11 ,
b11 -
1"
1%
1'
#550000000000000
0%
#555000000000000
0"
1%
#560000000000000
0%
#565000000000000
1%
0&
#570000000000000
0%
#575000000000000
0#
0/
b0 0
b0 -
1%
0)
#580000000000000
0%
#585000000000000
b0 $
b0 ,
1"
0+
0!
1%
#590000000000000
0%
#595000000000000
b1 0
1!
b1 -
0"
1.
1%
0'
1*
#600000000000000
0%
#605000000000000
0!
0.
1%
0*
#610000000000000
0%
#615000000000000
b10 0
1!
b10 -
b10 $
b10 ,
1"
1%
1)
#620000000000000
0%
#625000000000000
0"
1%
1&
#630000000000000
0%
#635000000000000
1#
1/
b11 0
b11 $
b11 ,
b11 -
1"
1%
1'
#640000000000000
0%
0'
#645000000000000
0"
1%
#650000000000000
0%
1(
#655000000000000
0#
0/
b0 0
b0 -
1%
#660000000000000
0%
#665000000000000
0!
1%
