6111work/Labs/Lab4/Lab4/Lab4.srcs/sources_1/new/fuel_pump_controller.v
module fuel_pump_controller( clk_in,
                             reset_in, // Probably attach this to the reprogram
                             brake_in, 
                             hidden_switch_in, 
                             ignition_in, 
                             fuel_power_out);
         input  clk_in;
         input  reset_in;
         input  brake_in;
         input  hidden_switch_in;
         input  ignition_in;
         output fuel_power_out;
         
         reg ignition_on    = 1'b0;
         reg fuel_power_out = 1'b0;
         
         always @(posedge clk_in or posedge reset_in)
         begin
            if (reset_in)
            begin
                ignition_on <= 1'b0;
                fuel_power_out <= 1'b0;
            end
            else
            begin
                if (fuel_power_out & (~ignition_in))
                begin
                    ignition_on <= 1'b0;
                    fuel_power_out <= 1'b0;
                end
                else 
                begin
                    if (brake_in & hidden_switch_in)
                    begin
                        if (ignition_on)
                        begin
                            fuel_power_out <= 1'b1;
                        end
                    end
                    else if (ignition_in & (~ignition_on))
                    begin
                        ignition_on <= 1'b1;
                    end
                end
            end
         
         end 
                  
endmodule

6111work/Labs/Lab4/Lab4/Lab4.srcs/sources_1/new/fuel_pump_controller_tb.v
module fuel_pump_controller_tb;
	reg  clk             = 1'b0;
	reg  reset           = 1'b1;
	reg  brake           = 1'b0;
	reg  hidden_switch   = 1'b0;
	reg  ignition        = 1'b0;
	
	wire fuel_power;
	
	fuel_pump_controller fpc1(
							.clk_in(clk),
							.reset_in(reset),
							.brake_in(brake),
							.hidden_switch_in(hidden_switch),
							.ignition_in(ignition),
							.fuel_power_out(fuel_power)
					    );

	initial
	begin
		$dumpfile("fuel_test.vcd");
		$dumpvars(0, fuel_pump_controller_tb);
		reset           = 1'b1;
		brake           = 1'b0;
		hidden_switch   = 1'b0;
		ignition        = 1'b0;
		#10;
		reset           = 1'b0;
		brake           = 1'b1;
		hidden_switch   = 1'b1;
		ignition        = 1'b1;
		#100; // Fuel power should stay 0
		ignition        = 1'b0;
		#10;
		brake           = 1'b0;
		hidden_switch   = 1'b0;
		#10;
		ignition        = 1'b0;
		#10;
		ignition        = 1'b1;
		#10;
		hidden_switch   = 1'b1;
		#5;
		ignition        = 1'b0;
		#10;
		brake           = 1'b1;
		#10;
		ignition        = 1'b1;
		#10;
		brake           = 1'b1;
		hidden_switch   = 1'b1;
		#10;
		ignition        = 1'b0;
		#500;
		$finish;
	end

	always #5 clk = ~clk;
endmodule

6111work/Labs/Lab4/Lab4/Lab4.srcs/sources_1/new/fuel_test.vcd
$date
	Wed Oct 10 14:41:06 2018
$end
$version
	Icarus Verilog
$end
$timescale
	1s
$end
$scope module fuel_pump_controller_tb $end
$var wire 1 ! fuel_power $end
$var reg 1 " brake $end
$var reg 1 # clk $end
$var reg 1 $ hidden_switch $end
$var reg 1 % ignition $end
$var reg 1 & reset $end
$scope module fpc1 $end
$var wire 1 " brake_in $end
$var wire 1 # clk_in $end
$var wire 1 $ hidden_switch_in $end
$var wire 1 % ignition_in $end
$var wire 1 & reset_in $end
$var reg 1 ! fuel_power_out $end
$var reg 1 ' ignition_on $end
$upscope $end
$upscope $end
$enddefinitions $end
#0
$dumpvars
0'
1&
0%
0$
0#
0"
0!
$end
#5
1#
#10
0#
1%
1$
1"
0&
#15
1#
#20
0#
#25
1#
#30
0#
#35
1#
#40
0#
#45
1#
#50
0#
#55
1#
#60
0#
#65
1#
#70
0#
#75
1#
#80
0#
#85
1#
#90
0#
#95
1#
#100
0#
#105
1#
#110
0#
0%
#115
1#
#120
0#
0$
0"
#125
1#
#130
0#
#135
1#
#140
0#
1%
#145
1'
1#
#150
0#
1$
#155
1#
0%
#160
0#
#165
1!
1#
1"
#170
0#
#175
1#
1%
#180
0#
#185
1#
#190
0#
#195
0!
0'
1#
0%
