6111work/Labs/Lab4/Lab4/Lab4.srcs/sources_1/new/timer.v
module timer ( clk_1hz_in,  start_in, value_in, expire_out );
    input       clk_1hz_in;
    input       start_in;
    input [3:0] value_in;
    output reg  expire_out;
    
    reg [3:0] counter = 4'b1;
    reg       started = 1'b0;
    always @(posedge clk_1hz_in or posedge start_in)
    begin
        if (start_in & ~started)
        begin
            started    <= 1'b1;
            expire_out <= 1'b0;
            counter <= value_in;
        end
        else
        begin
            if (counter == 0)
            begin
                started    <= 1'b0;
                counter    <= 0;
                expire_out <= 1'b1;
            end
            else
            begin
                counter <= counter - 1;
            end           
        end
    end
    
endmodule

6111work/Labs/Lab4/Lab4/Lab4.srcs/sources_1/new/timer_tb.v
module timer_tb;
	reg clk   = 1'b0;
	reg start    = 1'b0;
	reg [3:0] value = 4'b0;
	wire expired;

	timer t1(.clk_1hz_in(clk), .start_in(start), .value_in(value), .expire_out(expired));

	initial
	begin
		$dumpfile("timer_test.vcd");
		$dumpvars(0, timer_tb);
		value = 4'b0;
		start    = 1'b0;
		#10;
		value = 4'd10;
		#10;
		start    = 1'b1;
		#500;
		start    = 1'b0;
		#500;
		value = 4'd2;
		start    = 1'b1;
		#1000;
		$finish;
	end

	always #5 clk = ~clk;
endmodule

6111work/Labs/Lab4/Lab4/Lab4.srcs/sources_1/new/timer_test.vcd
$date
	Wed Oct 10 09:09:59 2018
$end
$version
	Icarus Verilog
$end
$timescale
	1s
$end
$scope module timer_tb $end
$var wire 1 ! expired $end
$var reg 1 " clk $end
$var reg 1 # start $end
$var reg 4 $ value [3:0] $end
$scope module t1 $end
$var wire 1 " clk_1hz_in $end
$var wire 1 # start_in $end
$var wire 4 % value_in [3:0] $end
$var reg 4 & counter [3:0] $end
$var reg 1 ! expire_out $end
$var reg 1 ' started $end
$upscope $end
$upscope $end
$enddefinitions $end
#0
$dumpvars
0'
b1 &
b0 %
b0 $
0#
0"
x!
$end
#5
b0 &
1"
#10
0"
b1010 $
b1010 %
#15
1!
1"
#20
b1010 &
0!
1'
0"
1#
#25
b1001 &
1"
#30
0"
#35
b1000 &
1"
#40
0"
#45
b111 &
1"
#50
0"
#55
b110 &
1"
#60
0"
#65
b101 &
1"
#70
0"
#75
b100 &
1"
#80
0"
#85
b11 &
1"
#90
0"
#95
b10 &
1"
#100
0"
#105
b1 &
1"
#110
0"
#115
b0 &
1"
#120
0"
#125
1!
0'
1"
#130
0"
#135
b1010 &
0!
1'
1"
#140
0"
#145
b1001 &
1"
#150
0"
#155
b1000 &
1"
#160
0"
#165
b111 &
1"
#170
0"
#175
b110 &
1"
#180
0"
#185
b101 &
1"
#190
0"
#195
b100 &
1"
#200
0"
#205
b11 &
1"
#210
0"
#215
b10 &
1"
#220
0"
#225
b1 &
1"
#230
0"
#235
b0 &
1"
#240
0"
#245
1!
0'
1"
#250
0"
#255
b1010 &
0!
1'
1"
#260
0"
#265
b1001 &
1"
#270
0"
#275
b1000 &
1"
#280
0"
#285
b111 &
1"
#290
0"
#295
b110 &
1"
#300
0"
#305
b101 &
1"
#310
0"
#315
b100 &
1"
#320
0"
#325
b11 &
1"
#330
0"
#335
b10 &
1"
#340
0"
#345
b1 &
1"
#350
0"
#355
b0 &
1"
#360
0"
#365
1!
0'
1"
#370
0"
#375
b1010 &
0!
1'
1"
#380
0"
#385
b1001 &
1"
#390
0"
#395
b1000 &
1"
#400
0"
#405
b111 &
1"
#410
0"
#415
b110 &
1"
#420
0"
#425
b101 &
1"
#430
0"
#435
b100 &
1"
#440
0"
#445
b11 &
1"
#450
0"
#455
b10 &
1"
#460
0"
#465
b1 &
1"
#470
0"
#475
b0 &
1"
#480
0"
#485
1!
0'
1"
#490
0"
#495
b1010 &
0!
1'
1"
#500
0"
#505
b1001 &
1"
#510
0"
#515
b1000 &
1"
#520
0"
0#
#525
b111 &
1"
#530
0"
#535
b110 &
1"
#540
0"
#545
b101 &
1"
#550
0"
#555
b100 &
1"
#560
0"
#565
b11 &
1"
#570
0"
#575
b10 &
1"
#580
0"
#585
b1 &
1"
#590
0"
#595
b0 &
1"
#600
0"
#605
1!
0'
1"
