6111work/PSets/Week 5/mem_controller.v
module mem_controller(
						input        clk_in,
						input        req_in,
						output       ras_out,
						output       mux_out,
						output       cas_out
					);

	localparam STATE_IDLE = 3'b000;
	localparam STATE_ROW  = 3'b001;
	localparam STATE_MUX  = 3'b011;
	localparam STATE_COL  = 3'b010;
	localparam STATE_HOLD = 3'b110;

	reg [2:0] state = STATE_IDLE;

	assign ras_out = (state == STATE_IDLE);
	assign mux_out = ~((state == STATE_IDLE) | (state == STATE_ROW));
	assign cas_out = ((state == STATE_IDLE) | (state == STATE_ROW) | (state == STATE_MUX));

	// state machine
	always @(posedge clk_in)
	begin
		case (state)
			STATE_IDLE : state <= req_in ? STATE_ROW : STATE_IDLE;
			STATE_ROW  : state <= STATE_MUX;
			STATE_MUX  : state <= STATE_COL;
			STATE_COL  : state <= STATE_HOLD;
			STATE_HOLD : state <= STATE_IDLE;
		endcase
	end

endmodule

6111work/PSets/Week 5/mem_controller_tb.v
`define assert(signal, value) \
        if (signal !== value) \
        begin \
            $display("ASSERTION FAILED in %m at time %0t: signal != value", $time); \
        end

module mem_controller_tb;
	reg        clk;
	reg        req;
	wire       ras;
	wire       mux;
	wire       cas;
	reg [2:0]  clk_counter;

	initial
	begin
	    $dumpfile("test.vcd");
		$dumpvars(0,mem_controller_tb);
		clk         = 0;
		clk_counter = 0;
		req         = 0;
		
		#2;
		req = 1;
		
		#11;
		req = 0;
		#50;
		$finish;
	end


	mem_controller m1(
						.clk_in    (clk),
						.req_in    (req),
						.ras_out   (ras),
						.mux_out   (mux),
						.cas_out   (cas)
						);

	always @(posedge clk)
	begin
		if ((clk_counter > 0) | ((req == 1) & (clk_counter == 0)))
		begin
			clk_counter = clk_counter + 1;

			if (clk_counter == 1)
			begin
				`assert(ras, 0);
				`assert(mux, 0);
				`assert(cas, 1);				
			end
			else if (clk_counter == 2)
			begin
				`assert(ras, 0);
				`assert(mux, 1);
				`assert(cas, 1);				
			end
			else if (clk_counter == 3)
			begin
				`assert(ras, 0);
				`assert(mux, 1);
				`assert(cas, 0);
			end
			else
			begin
				`assert(ras, 0);
				`assert(mux, 1);
				`assert(cas, 0);
				clk_counter = 0;
			end
		end
	end

	always #5 clk = ~clk;

endmodule

6111work/PSets/Week 5/test.vcd
$date
	Sun Sep 23 14:31:04 2018
$end
$version
	Icarus Verilog
$end
$timescale
	1s
$end
$scope module mem_controller_tb $end
$var wire 1 ! ras $end
$var wire 1 " mux $end
$var wire 1 # cas $end
$var reg 1 $ clk $end
$var reg 3 % clk_counter [2:0] $end
$var reg 1 & req $end
$scope module m1 $end
$var wire 1 # cas_out $end
$var wire 1 $ clk_in $end
$var wire 1 " mux_out $end
$var wire 1 & req_in $end
$var wire 1 ! ras_out $end
$var reg 3 ' state [2:0] $end
$upscope $end
$upscope $end
$enddefinitions $end
#0
$dumpvars
b0 '
0&
b0 %
0$
1#
0"
1!
$end
#2
1&
#5
0!
b1 '
b1 %
1$
#10
0$
#13
0&
#15
1"
b11 '
b10 %
1$
#20
0$
#25
0#
b10 '
b11 %
1$
#30
0$
#35
b110 '
b0 %
1$
#40
0$
#45
0"
1#
1!
b0 '
1$
