6111work/PSets/Week 6/lpset6.v
module lpset6(clock, start, data, done, r);
    input clock, start, data;
    output done;
    output [15:0] r;

    reg start_latch          = 1'b0;

    reg [15:0] r             = 16'hFFFF;
    // 64 - 16 = 48
    reg [6:0] counter        = 7'd31;
    wire [6:0] counter_next;

    assign done = counter_next[6];
    assign counter_next = counter + 1;

    always @ (posedge clock)
    begin
        if (start)
        begin
            start_latch <= 1'b1;
            r           <= 16'hFFFF;
            counter     <= 7'd31;
        end
        else 
        begin
            if (start_latch & (~counter_next[6]))
            begin
                r <=  {r[15] ^ r[14] ^ data, 
                                    r[13:2], 
                        r[15] ^ data ^ r[1], 
                                       r[0], 
                               r[15] ^ data
                      };
                counter <= counter_next;
            end
            else 
            begin
                start_latch <= 1'b0;
                // If you don't want done to stay high, uncomment below
                // counter <= 7'd32;
            end
        end
    end

endmodule

6111work/PSets/Week 6/crc_tf.v
`timescale 1ns / 1ps
/////////////////////////////////////////////////////////////////////////////
//
// lpset CRC test bench  9/29/2017
//
/////////////////////////////////////////////////////////////////////////////

module crc_tf;

   // Inputs
   reg clock;
   reg data_clk;
   reg start;
   reg data;

   // Outputs
   wire done;
   wire [15:0] r;

   // Instantiate the Unit Under Test (UUT)
   lpset6 uut (
      .clock(clock), 
      .start(start), 
      .data(data), 
      .done(done), 
      .r(r)
   );

   // this is the input data
   reg [31:0] input_data = 32'h03_01_02_03;
   integer i;      // required for "for" loop

   initial 
   begin   // system clock
      forever #5 clock = !clock;
   end
      
   initial 
   begin   // data_clk, ensures setup time met               
      #2
      forever #5 data_clk = !data_clk;
   end
      
   initial 
   begin
      $dumpfile("test.vcd");
      $dumpvars(0,crc_tf);
      // Initialize Inputs
      clock = 0;
      data_clk = 0;
      start = 0;
      data = 0;

      // Wait 100 ns for global reset to finish
      #100;
        
      // Add stimulus here
      start=1;
      #10 start = 0;
      #5;   // change if necessary for your design

      for (i=0; i<48; i=i+1)
      begin
         data = input_data[31];
         // at each clock, left shift the data
         // note syntax for test bench "for" loop - no "always"
         // note the blocking assignment (immediate)
         @(posedge data_clk) input_data = {input_data[31:0],1'b0};     
      end

      #5;
      $finish;
      
   end
      
endmodule

6111work/PSets/Week 6/test.vcd
$date
	Sun Oct 14 15:23:54 2018
$end
$version
	Icarus Verilog
$end
$timescale
	1ps
$end
$scope module crc_tf $end
$var wire 16 ! r [15:0] $end
$var wire 1 " done $end
$var reg 1 # clock $end
$var reg 1 $ data $end
$var reg 1 % data_clk $end
$var reg 32 & input_data [31:0] $end
$var reg 1 ' start $end
$var integer 32 ( i [31:0] $end
$scope module uut $end
$var wire 1 # clock $end
$var wire 1 $ data $end
$var wire 1 ' start $end
$var wire 1 " done $end
$var wire 7 ) counter_next [6:0] $end
$var reg 7 * counter [6:0] $end
$var reg 16 + r [15:0] $end
$var reg 1 , start_latch $end
$upscope $end
$upscope $end
$enddefinitions $end
#0
$dumpvars
0,
b1111111111111111 +
b11111 *
b100000 )
bx (
0'
b11000000010000001000000011 &
0%
0$
0#
0"
b1111111111111111 !
$end
#5000
1#
#7000
1%
#10000
0#
#12000
0%
#15000
1#
#17000
1%
#20000
0#
#22000
0%
#25000
1#
#27000
1%
#30000
0#
#32000
0%
#35000
1#
#37000
1%
#40000
0#
#42000
0%
#45000
1#
#47000
1%
#50000
0#
#52000
0%
#55000
1#
#57000
1%
#60000
0#
#62000
0%
#65000
1#
#67000
1%
#70000
0#
#72000
0%
#75000
1#
#77000
1%
#80000
0#
#82000
0%
#85000
1#
#87000
1%
#90000
0#
#92000
0%
#95000
1#
#97000
1%
#100000
0#
1'
#102000
0%
#105000
1,
1#
#107000
1%
#110000
0#
0'
#112000
0%
#115000
b100001 )
b100000 *
b111111111111011 !
b111111111111011 +
1#
b0 (
#117000
b1 (
b110000000100000010000000110 &
1%
#120000
0#
#122000
0%
#125000
b100010 )
b100001 *
b1111111111110110 !
b1111111111110110 +
1#
#127000
b10 (
b1100000001000000100000001100 &
1%
#130000
0#
#132000
0%
#135000
b100011 )
b100010 *
b111111111101001 !
b111111111101001 +
1#
#137000
b11 (
b11000000010000001000000011000 &
1%
#140000
0#
#142000
0%
#145000
b100100 )
b100011 *
b1111111111010010 !
b1111111111010010 +
1#
#147000
b100 (
b110000000100000010000000110000 &
1%
#150000
0#
#152000
0%
#155000
b100101 )
b100100 *
b111111110100001 !
b111111110100001 +
1#
#157000
b101 (
b1100000001000000100000001100000 &
1%
#160000
0#
#162000
0%
#165000
b100110 )
b100101 *
b1111111101000010 !
b1111111101000010 +
1#
#167000
1$
b110 (
b11000000010000001000000011000000 &
1%
#170000
0#
#172000
0%
#175000
b100111 )
b100110 *
b1111111010000100 !
b1111111010000100 +
1#
#177000
b111 (
b10000000100000010000000110000000 &
1%
#180000
0#
#182000
0%
#185000
b101000 )
b100111 *
b1111110100001000 !
b1111110100001000 +
1#
#187000
0$
b1000 (
b1000000100000001100000000 &
1%
#190000
0#
#192000
0%
#195000
b101001 )
b101000 *
b111101000010101 !
b111101000010101 +
1#
#197000
b1001 (
b10000001000000011000000000 &
1%
#200000
0#
#202000
0%
#205000
b101010 )
b101001 *
b1111010000101010 !
b1111010000101010 +
1#
#207000
b1010 (
b100000010000000110000000000 &
1%
#210000
0#
#212000
0%
#215000
b101011 )
b101010 *
b110100001010001 !
b110100001010001 +
1#
#217000
b1011 (
b1000000100000001100000000000 &
1%
#220000
0#
#222000
0%
#225000
b101100 )
b101011 *
b1101000010100010 !
b1101000010100010 +
1#
#227000
b1100 (
b10000001000000011000000000000 &
1%
#230000
0#
#232000
0%
#235000
b101101 )
b101100 *
b10000101000001 !
b10000101000001 +
1#
#237000
b1101 (
b100000010000000110000000000000 &
1%
#240000
0#
#242000
0%
#245000
b101110 )
b101101 *
b100001010000010 !
b100001010000010 +
1#
#247000
b1110 (
b1000000100000001100000000000000 &
1%
#250000
0#
#252000
0%
#255000
b101111 )
b101110 *
b1000010100000100 !
b1000010100000100 +
1#
#257000
1$
b1111 (
b10000001000000011000000000000000 &
1%
#260000
0#
#262000
0%
#265000
b110000 )
b101111 *
b101000001000 !
b101000001000 +
1#
#267000
0$
b10000 (
b10000000110000000000000000 &
1%
#270000
0#
#272000
0%
#275000
b110001 )
b110000 *
b1010000010000 !
b1010000010000 +
1#
#277000
b10001 (
b100000001100000000000000000 &
1%
#280000
0#
#282000
0%
#285000
b110010 )
b110001 *
b10100000100000 !
b10100000100000 +
1#
#287000
b10010 (
b1000000011000000000000000000 &
1%
#290000
0#
#292000
0%
#295000
b110011 )
b110010 *
b101000001000000 !
b101000001000000 +
1#
#297000
b10011 (
b10000000110000000000000000000 &
1%
#300000
0#
#302000
0%
#305000
b110100 )
b110011 *
b1010000010000000 !
b1010000010000000 +
1#
#307000
b10100 (
b100000001100000000000000000000 &
1%
#310000
0#
#312000
0%
#315000
b110101 )
b110100 *
b1100000100000101 !
b1100000100000101 +
1#
#317000
b10101 (
b1000000011000000000000000000000 &
1%
#320000
0#
#322000
0%
#325000
b110110 )
b110101 *
b1000001111 !
b1000001111 +
1#
#327000
1$
b10110 (
b10000000110000000000000000000000 &
1%
#330000
0#
#332000
0%
#335000
b110111 )
b110110 *
b1000010000011011 !
b1000010000011011 +
1#
#337000
0$
b10111 (
b1100000000000000000000000 &
1%
#340000
0#
#342000
0%
#345000
b111000 )
b110111 *
b1000100000110011 !
b1000100000110011 +
1#
#347000
b11000 (
b11000000000000000000000000 &
1%
#350000
0#
#352000
0%
#355000
b111001 )
b111000 *
b1001000001100011 !
b1001000001100011 +
1#
#357000
b11001 (
b110000000000000000000000000 &
1%
#360000
0#
#362000
0%
#365000
b111010 )
b111001 *
b1010000011000011 !
b1010000011000011 +
1#
#367000
b11010 (
b1100000000000000000000000000 &
1%
#370000
0#
#372000
0%
#375000
b111011 )
b111010 *
b1100000110000011 !
b1100000110000011 +
1#
#377000
b11011 (
b11000000000000000000000000000 &
1%
#380000
0#
#382000
0%
#385000
b111100 )
b111011 *
b1100000011 !
b1100000011 +
1#
#387000
b11100 (
b110000000000000000000000000000 &
1%
#390000
0#
#392000
0%
#395000
b111101 )
b111100 *
b11000000110 !
b11000000110 +
1#
#397000
b11101 (
b1100000000000000000000000000000 &
1%
#400000
0#
#402000
0%
#405000
b111110 )
b111101 *
b110000001100 !
b110000001100 +
1#
#407000
1$
b11110 (
b11000000000000000000000000000000 &
1%
#410000
0#
#412000
0%
#415000
b111111 )
b111110 *
b1001100000011101 !
b1001100000011101 +
1#
#417000
b11111 (
b10000000000000000000000000000000 &
1%
#420000
0#
#422000
0%
#425000
1"
b1000000 )
b111111 *
b11000000111010 !
b11000000111010 +
1#
#427000
0$
b100000 (
b0 &
1%
#430000
0#
#432000
0%
#435000
0,
1#
#437000
b100001 (
1%
#440000
0#
#442000
0%
#445000
1#
#447000
b100010 (
1%
#450000
0#
#452000
0%
#455000
1#
#457000
b100011 (
1%
#460000
0#
#462000
0%
#465000
1#
#467000
b100100 (
1%
#470000
0#
#472000
0%
#475000
1#
#477000
b100101 (
1%
#480000
0#
#482000
0%
#485000
1#
#487000
b100110 (
1%
#490000
0#
#492000
0%
#495000
1#
#497000
b100111 (
1%
#500000
0#
#502000
0%
#505000
1#
#507000
b101000 (
1%
#510000
0#
#512000
0%
#515000
1#
#517000
b101001 (
1%
#520000
0#
#522000
0%
#525000
1#
#527000
b101010 (
1%
#530000
0#
#532000
0%
#535000
1#
#537000
b101011 (
1%
#540000
0#
#542000
0%
#545000
1#
#547000
b101100 (
1%
#550000
0#
#552000
0%
#555000
1#
#557000
b101101 (
1%
#560000
0#
#562000
0%
#565000
1#
#567000
b101110 (
1%
#570000
0#
#572000
0%
#575000
1#
#577000
b101111 (
1%
#580000
0#
#582000
0%
#585000
1#
#587000
b110000 (
1%
