6111work/PSets/Week 7/convolutional_encoder.v
module convolutional_encoder(
								clk_in,
								start_in,
								data_in,
								done_out,
								fec_out
							);

	// This is the input clk, clk_in
	input			 clk_in;
	// This is the input start signal, start_in
	input			 start_in;
	// This is the input data signal, data_in
	// it is cereal.
	input			 data_in;
	// This is the done output signal
	output 		     done_out;
	// This is the 96 bit fec output signal 
	// given 48 bits input this block produces 2 outputs per input
	// 48 * 2 is 96
	output    [95:0] fec_out;

	// This is the local parameter window size
	localparam WIN_SIZE = 4;
	// This is the count value which we start decrementing from 
	// After 48 input cycles we are done
	localparam DONE_COUNT = 48;

	// This is the input data shift register. It is size 4 because
	// we need x[n-3]
	reg [WIN_SIZE-1:0] data_in_sr = 'b0;
	// This is the start state
	reg 			   started    = 1'b0;
	// This is the 96 bit fec output signal 
	// given 48 bits input this block produces 2 outputs per input
	// 48 * 2 is 96
	reg 		[95:0] fec_out    = 96'b0;
	// This is the counter to determine the number of bits in the shift 
	// register
	reg         [5:0]  counter    = DONE_COUNT;

	// This is a wire of P_0[n]
	wire p0;
	// This is a wire for P_1[n]
	wire p1;

	// This assigned the P_0[n] value to the value specified in the Pset
	assign p0       = data_in ^ data_in_sr[0] ^ data_in_sr[1] ^ data_in_sr[2];
	// This assigned the P_1[n] value to the value specified in the Pset
	assign p1       = data_in ^ data_in_sr[1] ^ data_in_sr[2];
	// We are done once the count hits 0
	assign done_out = ~(|counter); 

	//This is an always block so stuff is synchronous
	always @(posedge clk_in) 
	// This is the begin statement to look nice
	begin
		// This is an if statement which tells us to start if we 
		// get told to start but haven't started yet
		if ((~started) & start_in)
		// This is a begin statement to look nice
		begin
			// This is the beginning value of the counter
			counter    <= DONE_COUNT;
			// This initialised the fec_out to 0
			fec_out    <= 96'b0;
			// This tells us later that we have started
			started    <= 1'b1;
			// This is the shift in the shift register
			data_in_sr <= {data_in_sr[3:0], data_in};
			// This is an end statement for the if statement begin
		end
		// This is te check if we have started but aren't done yet
		else if (started & (~done_out))
		// This is the begin statement to look nice
		begin
			// This is the decrement of the counter
			counter    <= counter - 1;
			// This is the filling up of the fec register
			// We fill from the LSB
			fec_out    <= {fec_out[93:0], p1, p0};
			// This shifts the data into the shift register
			// We fill from the LSB
			data_in_sr <= {data_in_sr[3:0], data_in};
			// This is an end statement from the else if
		end
		// This is the end statement for the always block
	end
// This is an endmodule for the convolutional_encoder module
endmodule

6111work/PSets/Week 7/convolutional_encoder_tb.v
module convolutional_encoder_tb;
	// This is the count value which we start decrementing from 
	// After 48 input cycles we are done
	localparam DONE_COUNT = 48;
	// This is the clock
	reg         clk   = 1'b0;
	// This is the start signal
	reg         start = 1'b0;
	// This is the data signal
	reg         data  = 1'b0;
	// This is the done output signal
	wire        done;
	// This is the output of the FEC encoder
	wire [95:0] fec;
	// This is the instantiation of the FEC encoder
	convolutional_encoder ce1(
								.clk_in    (clk),
								.start_in  (start),
								.data_in   (data),
								.done_out  (done),
								.fec_out   (fec)
								);
	// This is the input test data
	reg [DONE_COUNT-1:0] data_sr = 48'h03010203303A;
	// This ensures that we haven't started yet, so do not 
	// shift data in
	reg                  started = 1'b0;

	// alonzi
	initial
	begin
		// This is so we can plot stuff in vcd viewer
		$dumpfile("test.vcd");
		// This is so we can see all the signals
		$dumpvars(0, convolutional_encoder_tb);
		// This tells the dut to start
		start   = 0;
		#10;
		start   = 1;
		// This is some delay so we get some output
		#500;
		// This is to deassert and make sure the 
		// output stays fixed
		start   = 0;
		#10;
		// bye bye
		$finish;
	end

	// This is the always block where we shift in the cereal data 
	always @(posedge clk) 
	begin
		// if we start or have started
		if ( (~done) & (start | started))
		begin
			// This is so we know next clock tick that we have started
			started <= 1'b1;
			// This puts the cereal into out encoder
			data    <= data_sr[DONE_COUNT-1];
			// This makes the cereal data
			data_sr <= {data_sr[DONE_COUNT-2:0], 1'b0};
		end
	end
	// This is how we clock
	always #5 clk = ~clk;
endmodule

6111work/PSets/Week 7/test.vcd
$date
	Mon Oct  8 08:16:37 2018
$end
$version
	Icarus Verilog
$end
$timescale
	1s
$end
$scope module convolutional_encoder_tb $end
$var wire 96 ! fec [95:0] $end
$var wire 1 " done $end
$var reg 1 # clk $end
$var reg 1 $ data $end
$var reg 48 % data_sr [47:0] $end
$var reg 1 & start $end
$var reg 1 ' started $end
$scope module ce1 $end
$var wire 1 # clk_in $end
$var wire 1 $ data_in $end
$var wire 1 " done_out $end
$var wire 1 ( p0 $end
$var wire 1 ) p1 $end
$var wire 1 & start_in $end
$var reg 6 * counter [5:0] $end
$var reg 4 + data_in_sr [3:0] $end
$var reg 96 , fec_out [95:0] $end
$var reg 1 - started $end
$upscope $end
$upscope $end
$enddefinitions $end
#0
$dumpvars
0-
b0 ,
b0 +
b110000 *
0)
0(
0'
0&
b110000000100000010000000110011000000111010 %
0$
0#
0"
b0 !
$end
#5
1#
#10
0#
1&
#15
b1100000001000000100000001100110000001110100 %
1'
1-
1#
#20
0#
#25
b101111 *
b11000000010000001000000011001100000011101000 %
1#
#30
0#
#35
b110000000100000010000000110011000000111010000 %
b101110 *
1#
#40
0#
#45
b101101 *
b1100000001000000100000001100110000001110100000 %
1#
#50
0#
#55
b11000000010000001000000011001100000011101000000 %
b101100 *
1#
#60
0#
#65
b101011 *
b110000000100000010000000110011000000111010000000 %
1#
#70
0#
#75
1(
1)
b100000001000000100000001100110000001110100000000 %
1$
b101010 *
1#
#80
0#
#85
0(
b1 +
b11 !
b11 ,
b101001 *
b10000001000000011001100000011101000000000 %
1#
#90
0#
#95
b100000010000000110011000000111010000000000 %
0$
b11 +
b1110 !
b1110 ,
b101000 *
1#
#100
0#
#105
0(
0)
b110 +
b111010 !
b111010 ,
b100111 *
b1000000100000001100110000001110100000000000 %
1#
#110
0#
#115
1(
1)
b10000001000000011001100000011101000000000000 %
b1100 +
b11101000 !
b11101000 ,
b100110 *
1#
#120
0#
#125
0(
0)
b1000 +
b1110100011 !
b1110100011 ,
b100101 *
b100000010000000110011000000111010000000000000 %
1#
#130
0#
#135
b1000000100000001100110000001110100000000000000 %
b0 +
b111010001100 !
b111010001100 ,
b100100 *
1#
#140
0#
#145
b11101000110000 !
b11101000110000 ,
b100011 *
b10000001000000011001100000011101000000000000000 %
1#
#150
0#
#155
b100000010000000110011000000111010000000000000000 %
b1110100011000000 !
b1110100011000000 ,
b100010 *
1#
#160
0#
#165
1(
1)
b111010001100000000 !
b111010001100000000 ,
b100001 *
b100000001100110000001110100000000000000000 %
1$
1#
#170
0#
#175
0)
b1000000011001100000011101000000000000000000 %
0$
b1 +
b11101000110000000011 !
b11101000110000000011 ,
b100000 *
1#
#180
0#
#185
1(
1)
b10 +
b1110100011000000001101 !
b1110100011000000001101 ,
b11111 *
b10000000110011000000111010000000000000000000 %
1#
#190
0#
#195
1(
1)
b100000001100110000001110100000000000000000000 %
b100 +
b111010001100000000110111 !
b111010001100000000110111 ,
b11110 *
1#
#200
0#
#205
0(
0)
b1000 +
b11101000110000000011011111 !
b11101000110000000011011111 ,
b11101 *
b1000000011001100000011101000000000000000000000 %
1#
#210
0#
#215
b10000000110011000000111010000000000000000000000 %
b0 +
b1110100011000000001101111100 !
b1110100011000000001101111100 ,
b11100 *
1#
#220
0#
#225
b111010001100000000110111110000 !
b111010001100000000110111110000 ,
b11011 *
b100000001100110000001110100000000000000000000000 %
1#
#230
0#
#235
1(
1)
b11001100000011101000000000000000000000000 %
1$
b11101000110000000011011111000000 !
b11101000110000000011011111000000 ,
b11010 *
1#
#240
0#
#245
1(
0)
b1 +
b1110100011000000001101111100000011 !
b1110100011000000001101111100000011 ,
b11001 *
b110011000000111010000000000000000000000000 %
0$
1#
#250
0#
#255
1(
1)
b1100110000001110100000000000000000000000000 %
b10 +
b111010001100000000110111110000001101 !
b111010001100000000110111110000001101 ,
b11000 *
1#
#260
0#
#265
1(
1)
b100 +
b11101000110000000011011111000000110111 !
b11101000110000000011011111000000110111 ,
b10111 *
b11001100000011101000000000000000000000000000 %
1#
#270
0#
#275
0(
0)
b110011000000111010000000000000000000000000000 %
b1000 +
b1110100011000000001101111100000011011111 !
b1110100011000000001101111100000011011111 ,
b10110 *
1#
#280
0#
#285
b0 +
b111010001100000000110111110000001101111100 !
b111010001100000000110111110000001101111100 ,
b10101 *
b1100110000001110100000000000000000000000000000 %
1#
#290
0#
#295
b11001100000011101000000000000000000000000000000 %
b11101000110000000011011111000000110111110000 !
b11101000110000000011011111000000110111110000 ,
b10100 *
1#
#300
0#
#305
b1110100011000000001101111100000011011111000000 !
b1110100011000000001101111100000011011111000000 ,
b10011 *
b110011000000111010000000000000000000000000000000 %
1#
#310
0#
#315
1(
1)
b100110000001110100000000000000000000000000000000 %
1$
b111010001100000000110111110000001101111100000000 !
b111010001100000000110111110000001101111100000000 ,
b10010 *
1#
#320
0#
#325
0(
b1 +
b11101000110000000011011111000000110111110000000011 !
b11101000110000000011011111000000110111110000000011 ,
b10001 *
b1100000011101000000000000000000000000000000000 %
1#
#330
0#
#335
b11000000111010000000000000000000000000000000000 %
0$
b11 +
b1110100011000000001101111100000011011111000000001110 !
b1110100011000000001101111100000011011111000000001110 ,
b10000 *
1#
#340
0#
#345
0(
0)
b110 +
b111010001100000000110111110000001101111100000000111010 !
b111010001100000000110111110000001101111100000000111010 ,
b1111 *
b110000001110100000000000000000000000000000000000 %
1#
#350
0#
#355
b100000011101000000000000000000000000000000000000 %
1$
b1100 +
b11101000110000000011011111000000110111110000000011101000 !
b11101000110000000011011111000000110111110000000011101000 ,
b1110 *
1#
#360
0#
#365
0(
1)
b1001 +
b1110100011000000001101111100000011011111000000001110100000 !
b1110100011000000001101111100000011011111000000001110100000 ,
b1101 *
b111010000000000000000000000000000000000000 %
1#
#370
0#
#375
b1110100000000000000000000000000000000000000 %
0$
b11 +
b111010001100000000110111110000001101111100000000111010000010 !
b111010001100000000110111110000001101111100000000111010000010 ,
b1100 *
1#
#380
0#
#385
0(
0)
b110 +
b11101000110000000011011111000000110111110000000011101000001010 !
b11101000110000000011011111000000110111110000000011101000001010 ,
b1011 *
b11101000000000000000000000000000000000000000 %
1#
#390
0#
#395
1(
1)
b111010000000000000000000000000000000000000000 %
b1100 +
b1110100011000000001101111100000011011111000000001110100000101000 !
b1110100011000000001101111100000011011111000000001110100000101000 ,
b1010 *
1#
#400
0#
#405
0(
0)
b1000 +
b111010001100000000110111110000001101111100000000111010000010100011 !
b111010001100000000110111110000001101111100000000111010000010100011 ,
b1001 *
b1110100000000000000000000000000000000000000000 %
1#
#410
0#
#415
b11101000000000000000000000000000000000000000000 %
b0 +
b11101000110000000011011111000000110111110000000011101000001010001100 !
b11101000110000000011011111000000110111110000000011101000001010001100 ,
b1000 *
1#
#420
0#
#425
b1110100011000000001101111100000011011111000000001110100000101000110000 !
b1110100011000000001101111100000011011111000000001110100000101000110000 ,
b111 *
b111010000000000000000000000000000000000000000000 %
1#
#430
0#
#435
1(
1)
b110100000000000000000000000000000000000000000000 %
1$
b111010001100000000110111110000001101111100000000111010000010100011000000 !
b111010001100000000110111110000001101111100000000111010000010100011000000 ,
b110 *
1#
#440
0#
#445
0(
b1 +
b11101000110000000011011111000000110111110000000011101000001010001100000011 !
b11101000110000000011011111000000110111110000000011101000001010001100000011 ,
b101 *
b101000000000000000000000000000000000000000000000 %
1#
#450
0#
#455
1(
0)
b10000000000000000000000000000000000000000000000 %
b11 +
b1110100011000000001101111100000011011111000000001110100000101000110000001110 !
b1110100011000000001101111100000011011111000000001110100000101000110000001110 ,
b100 *
1#
#460
0#
#465
b111 +
b111010001100000000110111110000001101111100000000111010000010100011000000111001 !
b111010001100000000110111110000001101111100000000111010000010100011000000111001 ,
b11 *
b100000000000000000000000000000000000000000000000 %
0$
1#
#470
0#
#475
1)
b0 %
1$
b1110 +
b11101000110000000011011111000000110111110000000011101000001010001100000011100101 !
b11101000110000000011011111000000110111110000000011101000001010001100000011100101 ,
b10 *
1#
#480
0#
#485
0(
1)
b1101 +
b1110100011000000001101111100000011011111000000001110100000101000110000001110010111 !
b1110100011000000001101111100000011011111000000001110100000101000110000001110010111 ,
b1 *
0$
1#
#490
0#
#495
1(
1)
1"
b1010 +
b111010001100000000110111110000001101111100000000111010000010100011000000111001011110 !
b111010001100000000110111110000001101111100000000111010000010100011000000111001011110 ,
b0 *
1#
#500
0#
#505
1#
#510
0#
0&
