6111work/PSets/Week 7/convolutional_encoder.v
module convolutional_encoder(
								clk_in,
								start_in,
								data_in,
								done_out,
								fec_out
							);

	input			 clk_in;
	input			 start_in;
	input			 data_in;
	output 		     done_out;
	output    [95:0] fec_out;


	localparam WIN_SIZE = 4;
	localparam DONE_COUNT = 48;

	reg [WIN_SIZE-1:0] data_in_sr = 'b0;
	reg 			   started    = 1'b0;
	reg 		[95:0] fec_out    = 96'b0;
	reg         [5:0]  counter    = DONE_COUNT;

	wire p0;
	wire p1;

	assign p0       = data_in ^ data_in_sr[0] ^ data_in_sr[1] ^ data_in_sr[2];
	assign p1       = data_in ^ data_in_sr[1] ^ data_in_sr[2];
	assign done_out = ~(|counter); 

	always @(posedge clk_in) 
	begin
		if ((~started) & start_in)
		begin
			counter    <= DONE_COUNT;
			fec_out    <= 96'b0;
			started    <= 1'b1;
			data_in_sr <= {data_in_sr[3:0], data_in};
		end
		else if (started & (~done_out))
		begin
			counter    <= counter - 1;
			fec_out    <= {fec_out[93:0], p1, p0};
			data_in_sr <= {data_in_sr[3:0], data_in};
		end
	end

endmodule

6111work/PSets/Week 7/convolutional_encoder_tb.v
module convolutional_encoder_tb;
	localparam DONE_COUNT = 48;
	
	reg         clk   = 1'b0;
	reg         start = 1'b0;
	reg         data  = 1'b0;
	wire        done;
	wire [95:0] fec;

	convolutional_encoder ce1(
								.clk_in    (clk),
								.start_in  (start),
								.data_in   (data),
								.done_out  (done),
								.fec_out   (fec)
								);

	reg [DONE_COUNT-1:0] data_sr = 48'h03010203303A;
	reg                  started = 1'b0;

	initial
	begin
		$dumpfile("test.vcd");
		$dumpvars(0, convolutional_encoder_tb);
		start   = 1;
		#10;
		start   = 1;
		#500;
		start   = 0;
		#10;
		$finish;
	end

	always @(posedge clk) 
	begin
		if (start | started)
		begin
			started <= 1'b1;
			data    <= data_sr[DONE_COUNT-1];
			data_sr <= {data_sr[DONE_COUNT-2:0], 1'b0};
		end
	end

	always #5 clk = ~clk;
endmodule

6111work/PSets/Week 7/test.vcd
$date
	Sun Oct  7 20:57:21 2018
$end
$version
	Icarus Verilog
$end
$timescale
	1s
$end
$scope module convolutional_encoder_tb $end
$var wire 96 ! fec [95:0] $end
$var wire 1 " done $end
$var reg 1 # clk $end
$var reg 1 $ data $end
$var reg 48 % data_sr [47:0] $end
$var reg 1 & start $end
$var reg 1 ' started $end
$scope module ce1 $end
$var wire 1 # clk_in $end
$var wire 1 $ data_in $end
$var wire 1 " done_out $end
$var wire 1 ( p0 $end
$var wire 1 ) p1 $end
$var wire 1 & start_in $end
$var reg 6 * counter [5:0] $end
$var reg 4 + data_in_sr [3:0] $end
$var reg 96 , fec_out [95:0] $end
$var reg 1 - started $end
$upscope $end
$upscope $end
$enddefinitions $end
#0
$dumpvars
0-
b0 ,
b0 +
b110000 *
0)
0(
0'
1&
b110000000100000010000000110011000000111010 %
0$
0#
0"
b0 !
$end
#5
1-
b1100000001000000100000001100110000001110100 %
1'
1#
#10
0#
#15
b11000000010000001000000011001100000011101000 %
b101111 *
1#
#20
0#
#25
b101110 *
b110000000100000010000000110011000000111010000 %
1#
#30
0#
#35
b1100000001000000100000001100110000001110100000 %
b101101 *
1#
#40
0#
#45
b101100 *
b11000000010000001000000011001100000011101000000 %
1#
#50
0#
#55
b110000000100000010000000110011000000111010000000 %
b101011 *
1#
#60
0#
#65
1(
1)
b101010 *
b100000001000000100000001100110000001110100000000 %
1$
1#
#70
0#
#75
0(
b10000001000000011001100000011101000000000 %
b1 +
b11 !
b11 ,
b101001 *
1#
#80
0#
#85
1)
b11 +
b1110 !
b1110 ,
b101000 *
b100000010000000110011000000111010000000000 %
0$
1#
#90
0#
#95
0(
0)
b1000000100000001100110000001110100000000000 %
b110 +
b111010 !
b111010 ,
b100111 *
1#
#100
0#
#105
1(
1)
b1100 +
b11101000 !
b11101000 ,
b100110 *
b10000001000000011001100000011101000000000000 %
1#
#110
0#
#115
0(
0)
b100000010000000110011000000111010000000000000 %
b1000 +
b1110100011 !
b1110100011 ,
b100101 *
1#
#120
0#
#125
b0 +
b111010001100 !
b111010001100 ,
b100100 *
b1000000100000001100110000001110100000000000000 %
1#
#130
0#
#135
b10000001000000011001100000011101000000000000000 %
b11101000110000 !
b11101000110000 ,
b100011 *
1#
#140
0#
#145
b1110100011000000 !
b1110100011000000 ,
b100010 *
b100000010000000110011000000111010000000000000000 %
1#
#150
0#
#155
1(
1)
b100000001100110000001110100000000000000000 %
1$
b111010001100000000 !
b111010001100000000 ,
b100001 *
1#
#160
0#
#165
1(
0)
b1 +
b11101000110000000011 !
b11101000110000000011 ,
b100000 *
b1000000011001100000011101000000000000000000 %
0$
1#
#170
0#
#175
1(
1)
b10000000110011000000111010000000000000000000 %
b10 +
b1110100011000000001101 !
b1110100011000000001101 ,
b11111 *
1#
#180
0#
#185
1(
1)
b100 +
b111010001100000000110111 !
b111010001100000000110111 ,
b11110 *
b100000001100110000001110100000000000000000000 %
1#
#190
0#
#195
0(
0)
b1000000011001100000011101000000000000000000000 %
b1000 +
b11101000110000000011011111 !
b11101000110000000011011111 ,
b11101 *
1#
#200
0#
#205
b0 +
b1110100011000000001101111100 !
b1110100011000000001101111100 ,
b11100 *
b10000000110011000000111010000000000000000000000 %
1#
#210
0#
#215
b100000001100110000001110100000000000000000000000 %
b111010001100000000110111110000 !
b111010001100000000110111110000 ,
b11011 *
1#
#220
0#
#225
1(
1)
b11101000110000000011011111000000 !
b11101000110000000011011111000000 ,
b11010 *
b11001100000011101000000000000000000000000 %
1$
1#
#230
0#
#235
0)
b110011000000111010000000000000000000000000 %
0$
b1 +
b1110100011000000001101111100000011 !
b1110100011000000001101111100000011 ,
b11001 *
1#
#240
0#
#245
1(
1)
b10 +
b111010001100000000110111110000001101 !
b111010001100000000110111110000001101 ,
b11000 *
b1100110000001110100000000000000000000000000 %
1#
#250
0#
#255
1(
1)
b11001100000011101000000000000000000000000000 %
b100 +
b11101000110000000011011111000000110111 !
b11101000110000000011011111000000110111 ,
b10111 *
1#
#260
0#
#265
0(
0)
b1000 +
b1110100011000000001101111100000011011111 !
b1110100011000000001101111100000011011111 ,
b10110 *
b110011000000111010000000000000000000000000000 %
1#
#270
0#
#275
b1100110000001110100000000000000000000000000000 %
b0 +
b111010001100000000110111110000001101111100 !
b111010001100000000110111110000001101111100 ,
b10101 *
1#
#280
0#
#285
b11101000110000000011011111000000110111110000 !
b11101000110000000011011111000000110111110000 ,
b10100 *
b11001100000011101000000000000000000000000000000 %
1#
#290
0#
#295
b110011000000111010000000000000000000000000000000 %
b1110100011000000001101111100000011011111000000 !
b1110100011000000001101111100000011011111000000 ,
b10011 *
1#
#300
0#
#305
1(
1)
b111010001100000000110111110000001101111100000000 !
b111010001100000000110111110000001101111100000000 ,
b10010 *
b100110000001110100000000000000000000000000000000 %
1$
1#
#310
0#
#315
0(
b1100000011101000000000000000000000000000000000 %
b1 +
b11101000110000000011011111000000110111110000000011 !
b11101000110000000011011111000000110111110000000011 ,
b10001 *
1#
#320
0#
#325
1)
b11 +
b1110100011000000001101111100000011011111000000001110 !
b1110100011000000001101111100000011011111000000001110 ,
b10000 *
b11000000111010000000000000000000000000000000000 %
0$
1#
#330
0#
#335
0(
0)
b110000001110100000000000000000000000000000000000 %
b110 +
b111010001100000000110111110000001101111100000000111010 !
b111010001100000000110111110000001101111100000000111010 ,
b1111 *
1#
#340
0#
#345
0)
b1100 +
b11101000110000000011011111000000110111110000000011101000 !
b11101000110000000011011111000000110111110000000011101000 ,
b1110 *
b100000011101000000000000000000000000000000000000 %
1$
1#
#350
0#
#355
0(
1)
b111010000000000000000000000000000000000000 %
b1001 +
b1110100011000000001101111100000011011111000000001110100000 !
b1110100011000000001101111100000011011111000000001110100000 ,
b1101 *
1#
#360
0#
#365
1)
b11 +
b111010001100000000110111110000001101111100000000111010000010 !
b111010001100000000110111110000001101111100000000111010000010 ,
b1100 *
b1110100000000000000000000000000000000000000 %
0$
1#
#370
0#
#375
0(
0)
b11101000000000000000000000000000000000000000 %
b110 +
b11101000110000000011011111000000110111110000000011101000001010 !
b11101000110000000011011111000000110111110000000011101000001010 ,
b1011 *
1#
#380
0#
#385
1(
1)
b1100 +
b1110100011000000001101111100000011011111000000001110100000101000 !
b1110100011000000001101111100000011011111000000001110100000101000 ,
b1010 *
b111010000000000000000000000000000000000000000 %
1#
#390
0#
#395
0(
0)
b1110100000000000000000000000000000000000000000 %
b1000 +
b111010001100000000110111110000001101111100000000111010000010100011 !
b111010001100000000110111110000001101111100000000111010000010100011 ,
b1001 *
1#
#400
0#
#405
b0 +
b11101000110000000011011111000000110111110000000011101000001010001100 !
b11101000110000000011011111000000110111110000000011101000001010001100 ,
b1000 *
b11101000000000000000000000000000000000000000000 %
1#
#410
0#
#415
b111010000000000000000000000000000000000000000000 %
b1110100011000000001101111100000011011111000000001110100000101000110000 !
b1110100011000000001101111100000011011111000000001110100000101000110000 ,
b111 *
1#
#420
0#
#425
1(
1)
b111010001100000000110111110000001101111100000000111010000010100011000000 !
b111010001100000000110111110000001101111100000000111010000010100011000000 ,
b110 *
b110100000000000000000000000000000000000000000000 %
1$
1#
#430
0#
#435
0(
b101000000000000000000000000000000000000000000000 %
b1 +
b11101000110000000011011111000000110111110000000011101000001010001100000011 !
b11101000110000000011011111000000110111110000000011101000001010001100000011 ,
b101 *
1#
#440
0#
#445
1(
0)
b11 +
b1110100011000000001101111100000011011111000000001110100000101000110000001110 !
b1110100011000000001101111100000011011111000000001110100000101000110000001110 ,
b100 *
b10000000000000000000000000000000000000000000000 %
1#
#450
0#
#455
1(
b100000000000000000000000000000000000000000000000 %
0$
b111 +
b111010001100000000110111110000001101111100000000111010000010100011000000111001 !
b111010001100000000110111110000001101111100000000111010000010100011000000111001 ,
b11 *
1#
#460
0#
#465
1(
1)
b1110 +
b11101000110000000011011111000000110111110000000011101000001010001100000011100101 !
b11101000110000000011011111000000110111110000000011101000001010001100000011100101 ,
b10 *
b0 %
1$
1#
#470
0#
#475
0(
0$
b1101 +
b1110100011000000001101111100000011011111000000001110100000101000110000001110010111 !
b1110100011000000001101111100000011011111000000001110100000101000110000001110010111 ,
b1 *
1#
#480
0#
#485
1(
1)
1"
b1010 +
b111010001100000000110111110000001101111100000000111010000010100011000000111001011110 !
b111010001100000000110111110000001101111100000000111010000010100011000000111001011110 ,
b0 *
1#
#490
0#
#495
1#
#500
0#
#505
1#
#510
0#
0&
